[
	{
		"i_Id": 11,
		"i_SkillId": 1,
		"i_SkillLevel": 1,
		"i_effectType": 0,
		"ill_effect": [
			[
				0
			]
		],
		"ill_effectcondition": [
			[
				0
			]
		],
		"s_ItemIcon": "awake_hero_1",
		"s_SkillDesc": "·剑气伤害增加至攻击的\u003ccolor=#FFAD54\u003e174%\u003c/color\u003e\n·剑光伤害增加至攻击的\u003ccolor=#FFAD54\u003e228%\u003c/color\u003e",
		"s_SkillInfoDesc": "战斗中，星级可突破5星\n并获得：剑气伤害增加至攻击的\u003ccolor=#FFAD54\u003e174%\u003c/color\u003e\n剑光伤害增加至攻击的\u003ccolor=#FFAD54\u003e228%\u003c/color\u003e",
		"s_SkillName": "秦王绕柱"
	},
	{
		"i_Id": 12,
		"i_SkillId": 1,
		"i_SkillLevel": 2,
		"i_effectType": 0,
		"ill_effect": [
			[
				0
			]
		],
		"ill_effectcondition": [
			[
				0
			]
		],
		"s_ItemIcon": "awake_hero_1",
		"s_SkillDesc": "·剑气伤害增加至攻击的\u003ccolor=#FFAD54\u003e203%\u003c/color\u003e\n·剑光伤害增加至攻击的\u003ccolor=#FFAD54\u003e266%\u003c/color\u003e\n·攻击时释放\u003ccolor=#FFAD54\u003e4\u003c/color\u003e道剑气",
		"s_SkillInfoDesc": "进入战斗后，可自动升至2星\n并获得：剑气伤害增加至攻击的\u003ccolor=#FFAD54\u003e203%\u003c/color\u003e\n剑光伤害增加至攻击的\u003ccolor=#FFAD54\u003e266%\u003c/color\u003e\n攻击时释放\u003ccolor=#FFAD54\u003e4\u003c/color\u003e道剑气",
		"s_SkillName": "秦王绕柱"
	},
	{
		"i_Id": 13,
		"i_SkillId": 1,
		"i_SkillLevel": 3,
		"i_effectType": 0,
		"ill_effect": [
			[
				0
			]
		],
		"ill_effectcondition": [
			[
				0
			]
		],
		"s_ItemIcon": "awake_hero_1",
		"s_SkillDesc": "·剑气伤害增加至攻击的\u003ccolor=#FFAD54\u003e232%\u003c/color\u003e\n·剑光伤害增加至攻击的\u003ccolor=#FFAD54\u003e304%\u003c/color\u003e\n·攻击时释放\u003ccolor=#FFAD54\u003e4\u003c/color\u003e道剑气",
		"s_SkillInfoDesc": "进入战斗后，可自动升至3星\n战斗中获得：剑气伤害增加至攻击的\u003ccolor=#FFAD54\u003e232%\u003c/color\u003e\n剑光伤害增加至攻击的\u003ccolor=#FFAD54\u003e304%\u003c/color\u003e",
		"s_SkillName": "秦王绕柱"
	},
	{
		"i_Id": 21,
		"i_SkillId": 2,
		"i_SkillLevel": 1,
		"i_effectType": 0,
		"ill_effect": [
			[
				0
			]
		],
		"ill_effectcondition": [
			[
				0
			]
		],
		"s_ItemIcon": "awake_hero_1",
		"s_SkillDesc": "·一闪伤害增加至攻击的\u003ccolor=#FFAD54\u003e360%\u003c/color\u003e\n·通灵术伤害增加至攻击的\u003ccolor=#FFAD54\u003e216%\u003c/color\u003e",
		"s_SkillInfoDesc": "战斗中，星级可突破5星\n并获得：一闪伤害增加至攻击的\u003ccolor=#FFAD54\u003e360%\u003c/color\u003e\n通灵术伤害增加至攻击的\u003ccolor=#FFAD54\u003e216%\u003c/color\u003e",
		"s_SkillName": "装遁"
	},
	{
		"i_Id": 22,
		"i_SkillId": 2,
		"i_SkillLevel": 2,
		"i_effectType": 0,
		"ill_effect": [
			[
				0
			]
		],
		"ill_effectcondition": [
			[
				0
			]
		],
		"s_ItemIcon": "awake_hero_1",
		"s_SkillDesc": "·一闪伤害增加至攻击的\u003ccolor=#FFAD54\u003e420%\u003c/color\u003e\n·通灵术伤害增加至攻击的\u003ccolor=#FFAD54\u003e252%\u003c/color\u003e\n·攻击时召唤\u003ccolor=#FFAD54\u003e4\u003c/color\u003e个分身",
		"s_SkillInfoDesc": "进入战斗后，可自动升至2星\n并获得：一闪伤害增加至攻击的\u003ccolor=#FFAD54\u003e420%\u003c/color\u003e\n通灵术伤害增加至攻击的\u003ccolor=#FFAD54\u003e252%\u003c/color\u003e\n攻击时召唤\u003ccolor=#FFAD54\u003e4\u003c/color\u003e个分身",
		"s_SkillName": "装遁"
	},
	{
		"i_Id": 23,
		"i_SkillId": 2,
		"i_SkillLevel": 3,
		"i_effectType": 0,
		"ill_effect": [
			[
				0
			]
		],
		"ill_effectcondition": [
			[
				0
			]
		],
		"s_ItemIcon": "awake_hero_1",
		"s_SkillDesc": "·一闪伤害增加至攻击的\u003ccolor=#FFAD54\u003e160%\u003c/color\u003e\n·通灵术伤害增加至攻击的\u003ccolor=#FFAD54\u003e288%\u003c/color\u003e\n·攻击时召唤\u003ccolor=#FFAD54\u003e4\u003c/color\u003e个分身",
		"s_SkillInfoDesc": "进入战斗后，可自动升至3星\n战斗中获得：一闪伤害增加至攻击的\u003ccolor=#FFAD54\u003e160%\u003c/color\u003e\n通灵术伤害增加至攻击的\u003ccolor=#FFAD54\u003e288%\u003c/color\u003e\n攻击时召唤\u003ccolor=#FFAD54\u003e4\u003c/color\u003e个分身",
		"s_SkillName": "装遁"
	},
	{
		"i_Id": 31,
		"i_SkillId": 3,
		"i_SkillLevel": 1,
		"i_effectType": 0,
		"ill_effect": [
			[
				0
			]
		],
		"ill_effectcondition": [
			[
				0
			]
		],
		"s_ItemIcon": "awake_hero_1",
		"s_SkillDesc": "·光球伤害增加至攻击的\u003ccolor=#FFAD54\u003e95%\u003c/color\u003e\n·巨型光球伤害增加至攻击的\u003ccolor=#FFAD54\u003e360%\u003c/color\u003e",
		"s_SkillInfoDesc": "战斗中，星级可突破5星\n并获得：光球伤害增加至攻击的\u003ccolor=#FFAD54\u003e95%\u003c/color\u003e\n巨型光球伤害增加至攻击的\u003ccolor=#FFAD54\u003e360%\u003c/color\u003e",
		"s_SkillName": "相对论"
	},
	{
		"i_Id": 32,
		"i_SkillId": 3,
		"i_SkillLevel": 2,
		"i_effectType": 0,
		"ill_effect": [
			[
				0
			]
		],
		"ill_effectcondition": [
			[
				0
			]
		],
		"s_ItemIcon": "awake_hero_1",
		"s_SkillDesc": "·光球伤害增加至攻击的\u003ccolor=#FFAD54\u003e110%\u003c/color\u003e\n·巨型光球伤害增加至攻击的\u003ccolor=#FFAD54\u003e420%\u003c/color\u003e\n·巨型光球增加到\u003ccolor=#FFAD54\u003e5\u003c/color\u003e个",
		"s_SkillInfoDesc": "进入战斗后，可自动升至2星\n并获得：光球伤害增加至攻击的\u003ccolor=#FFAD54\u003e110%\u003c/color\u003e\n巨型光球伤害增加至攻击的\u003ccolor=#FFAD54\u003e420%\u003c/color\u003e\n巨型光球增加到\u003ccolor=#FFAD54\u003e5\u003c/color\u003e个",
		"s_SkillName": "相对论"
	},
	{
		"i_Id": 33,
		"i_SkillId": 3,
		"i_SkillLevel": 3,
		"i_effectType": 0,
		"ill_effect": [
			[
				0
			]
		],
		"ill_effectcondition": [
			[
				0
			]
		],
		"s_ItemIcon": "awake_hero_1",
		"s_SkillDesc": "·光球伤害增加至攻击的\u003ccolor=#FFAD54\u003e126%\u003c/color\u003e\n·巨型光球伤害增加至攻击的\u003ccolor=#FFAD54\u003e480%\u003c/color\u003e\n·巨型光球增加到\u003ccolor=#FFAD54\u003e5\u003c/color\u003e个",
		"s_SkillInfoDesc": "进入战斗后，可自动升至3星\n战斗中获得：光球伤害增加至攻击的\u003ccolor=#FFAD54\u003e126%\u003c/color\u003e\n巨型光球伤害增加至攻击的\u003ccolor=#FFAD54\u003e480%\u003c/color\u003e",
		"s_SkillName": "相对论"
	},
	{
		"i_Id": 41,
		"i_SkillId": 4,
		"i_SkillLevel": 1,
		"i_effectType": 0,
		"ill_effect": [
			[
				0
			]
		],
		"ill_effectcondition": [
			[
				0
			]
		],
		"s_ItemIcon": "awake_hero_1",
		"s_SkillDesc": "·激光伤害增加至攻击的\u003ccolor=#FFAD54\u003e360%\u003c/color\u003e\n·引魂灯伤害增加至攻击的\u003ccolor=#FFAD54\u003e88%\u003c/color\u003e",
		"s_SkillInfoDesc": "战斗中，星级可突破5星\n并获得：激光伤害增加至攻击的\u003ccolor=#FFAD54\u003e360%\u003c/color\u003e\n引魂灯伤害增加至攻击的\u003ccolor=#FFAD54\u003e88%\u003c/color\u003e",
		"s_SkillName": "神圣誓言"
	},
	{
		"i_Id": 42,
		"i_SkillId": 4,
		"i_SkillLevel": 2,
		"i_effectType": 0,
		"ill_effect": [
			[
				0
			]
		],
		"ill_effectcondition": [
			[
				0
			]
		],
		"s_ItemIcon": "awake_hero_1",
		"s_SkillDesc": "·激光伤害增加至攻击的\u003ccolor=#FFAD54\u003e420%\u003c/color\u003e，并且可同时治疗\u003ccolor=#FFAD54\u003e4\u003c/color\u003e个英雄\n·引魂灯伤害增加至攻击的\u003ccolor=#FFAD54\u003e102%\u003c/color\u003e",
		"s_SkillInfoDesc": "进入战斗后，可自动升至2星\n并获得：激光伤害增加至攻击的\u003ccolor=#FFAD54\u003e420%\u003c/color\u003e，并且可同时治疗\u003ccolor=#FFAD54\u003e4\u003c/color\u003e个英雄\n引魂灯伤害增加至攻击的\u003ccolor=#FFAD54\u003e102%\u003c/color\u003e",
		"s_SkillName": "神圣誓言"
	},
	{
		"i_Id": 43,
		"i_SkillId": 4,
		"i_SkillLevel": 3,
		"i_effectType": 0,
		"ill_effect": [
			[
				0
			]
		],
		"ill_effectcondition": [
			[
				0
			]
		],
		"s_ItemIcon": "awake_hero_1",
		"s_SkillDesc": "·激光伤害增加至攻击的\u003ccolor=#FFAD54\u003e480%\u003c/color\u003e，并且可同时治疗\u003ccolor=#FFAD54\u003e4\u003c/color\u003e个英雄\n·引魂灯伤害增加至攻击的\u003ccolor=#FFAD54\u003e117%\u003c/color\u003e",
		"s_SkillInfoDesc": "进入战斗后，可自动升至3星\n战斗中获得：激光伤害增加至攻击的\u003ccolor=#FFAD54\u003e480%\u003c/color\u003e\n引魂灯伤害增加至攻击的\u003ccolor=#FFAD54\u003e117%\u003c/color\u003e",
		"s_SkillName": "神圣誓言"
	},
	{
		"i_Id": 51,
		"i_SkillId": 5,
		"i_SkillLevel": 1,
		"i_effectType": 0,
		"ill_effect": [
			[
				0
			]
		],
		"ill_effectcondition": [
			[
				0
			]
		],
		"s_ItemIcon": "awake_hero_1",
		"s_SkillDesc": "·子弹伤害增加至攻击的\u003ccolor=#FFAD54\u003e69%\u003c/color\u003e\n·飞刀伤害增加至攻击的\u003ccolor=#FFAD54\u003e144%\u003c/color\u003e",
		"s_SkillInfoDesc": "战斗中，星级可突破5星\n并获得：子弹伤害增加至攻击的\u003ccolor=#FFAD54\u003e69%\u003c/color\u003e\n飞刀伤害增加至攻击的\u003ccolor=#FFAD54\u003e144%\u003c/color\u003e",
		"s_SkillName": "花式犯贱"
	},
	{
		"i_Id": 52,
		"i_SkillId": 5,
		"i_SkillLevel": 2,
		"i_effectType": 0,
		"ill_effect": [
			[
				0
			]
		],
		"ill_effectcondition": [
			[
				0
			]
		],
		"s_ItemIcon": "awake_hero_1",
		"s_SkillDesc": "·子弹伤害增加至攻击的\u003ccolor=#FFAD54\u003e81%\u003c/color\u003e\n·飞刀伤害增加至攻击的\u003ccolor=#FFAD54\u003e168%\u003c/color\u003e\n·攻击时获得\u003ccolor=#FFAD54\u003e20%\u003c/color\u003e攻速",
		"s_SkillInfoDesc": "进入战斗后，可自动升至2星\n并获得：子弹伤害增加至攻击的\u003ccolor=#FFAD54\u003e81%\u003c/color\u003e\n飞刀伤害增加至攻击的\u003ccolor=#FFAD54\u003e168%\u003c/color\u003e\n攻击时获得\u003ccolor=#FFAD54\u003e20%\u003c/color\u003e攻速",
		"s_SkillName": "花式犯贱"
	},
	{
		"i_Id": 53,
		"i_SkillId": 5,
		"i_SkillLevel": 3,
		"i_effectType": 0,
		"ill_effect": [
			[
				0
			]
		],
		"ill_effectcondition": [
			[
				0
			]
		],
		"s_ItemIcon": "awake_hero_1",
		"s_SkillDesc": "·子弹伤害增加至攻击的\u003ccolor=#FFAD54\u003e92%\u003c/color\u003e\n·飞刀伤害增加至攻击的\u003ccolor=#FFAD54\u003e192%\u003c/color\u003e\n·攻击时获得\u003ccolor=#FFAD54\u003e20%\u003c/color\u003e攻速",
		"s_SkillInfoDesc": "进入战斗后，可自动升至3星\n战斗中获得：子弹伤害增加至攻击的\u003ccolor=#FFAD54\u003e92%\u003c/color\u003e\n飞刀伤害增加至攻击的\u003ccolor=#FFAD54\u003e192%\u003c/color\u003e\n攻击时获得\u003ccolor=#FFAD54\u003e20%\u003c/color\u003e攻速",
		"s_SkillName": "花式犯贱"
	},
	{
		"i_Id": 61,
		"i_SkillId": 6,
		"i_SkillLevel": 1,
		"i_effectType": 0,
		"ill_effect": [
			[
				0
			]
		],
		"ill_effectcondition": [
			[
				0
			]
		],
		"s_ItemIcon": "awake_hero_1",
		"s_SkillDesc": "·火箭伤害增加至攻击的\u003ccolor=#FFAD54\u003e103%\u003c/color\u003e\n·飞舰伤害增加至攻击的\u003ccolor=#FFAD54\u003e360%\u003c/color\u003e",
		"s_SkillInfoDesc": "战斗中，星级可突破5星\n并获得：火箭伤害增加至攻击的\u003ccolor=#FFAD54\u003e103%\u003c/color\u003e\n飞舰伤害增加至攻击的\u003ccolor=#FFAD54\u003e360%\u003c/color\u003e",
		"s_SkillName": "有害动物"
	},
	{
		"i_Id": 62,
		"i_SkillId": 6,
		"i_SkillLevel": 2,
		"i_effectType": 0,
		"ill_effect": [
			[
				0
			]
		],
		"ill_effectcondition": [
			[
				0
			]
		],
		"s_ItemIcon": "awake_hero_1",
		"s_SkillDesc": "·火箭伤害增加至攻击的\u003ccolor=#FFAD54\u003e120%\u003c/color\u003e\n·飞舰伤害增加至攻击的\u003ccolor=#FFAD54\u003e420%\u003c/color\u003e\n·每条飞舰轰炸\u003ccolor=#FFAD54\u003e14\u003c/color\u003e次",
		"s_SkillInfoDesc": "进入战斗后，可自动升至2星\n并获得：火箭伤害增加至攻击的\u003ccolor=#FFAD54\u003e120%\u003c/color\u003e\n飞舰伤害增加至攻击的\u003ccolor=#FFAD54\u003e420%\u003c/color\u003e\n每条飞舰轰炸\u003ccolor=#FFAD54\u003e14\u003c/color\u003e次",
		"s_SkillName": "有害动物"
	},
	{
		"i_Id": 63,
		"i_SkillId": 6,
		"i_SkillLevel": 3,
		"i_effectType": 0,
		"ill_effect": [
			[
				0
			]
		],
		"ill_effectcondition": [
			[
				0
			]
		],
		"s_ItemIcon": "awake_hero_1",
		"s_SkillDesc": "·火箭伤害增加至攻击的\u003ccolor=#FFAD54\u003e138%\u003c/color\u003e\n·飞舰伤害增加至攻击的\u003ccolor=#FFAD54\u003e480%\u003c/color\u003e\n·每条飞舰轰炸\u003ccolor=#FFAD54\u003e14\u003c/color\u003e次",
		"s_SkillInfoDesc": "进入战斗后，可自动升至3星\n战斗中获得：火箭伤害增加至攻击的\u003ccolor=#FFAD54\u003e138%\u003c/color\u003e\n飞舰伤害增加至攻击的\u003ccolor=#FFAD54\u003e480%\u003c/color\u003e",
		"s_SkillName": "有害动物"
	},
	{
		"i_Id": 71,
		"i_SkillId": 7,
		"i_SkillLevel": 1,
		"i_effectType": 0,
		"ill_effect": [
			[
				0
			]
		],
		"ill_effectcondition": [
			[
				0
			]
		],
		"s_ItemIcon": "awake_hero_1",
		"s_SkillDesc": "·水波伤害增加至攻击的\u003ccolor=#FFAD54\u003e132%\u003c/color\u003e\n·海浪伤害增加至攻击的\u003ccolor=#FFAD54\u003e300%\u003c/color\u003e",
		"s_SkillInfoDesc": "战斗中，星级可突破5星\n并获得：水波伤害增加至攻击的\u003ccolor=#FFAD54\u003e132%\u003c/color\u003e\n海浪伤害增加至攻击的\u003ccolor=#FFAD54\u003e300%\u003c/color\u003e",
		"s_SkillName": "血脉觉醒"
	},
	{
		"i_Id": 72,
		"i_SkillId": 7,
		"i_SkillLevel": 2,
		"i_effectType": 0,
		"ill_effect": [
			[
				0
			]
		],
		"ill_effectcondition": [
			[
				0
			]
		],
		"s_ItemIcon": "awake_hero_1",
		"s_SkillDesc": "·水波伤害增加至攻击的\u003ccolor=#FFAD54\u003e154%\u003c/color\u003e\n·海浪伤害增加至攻击的\u003ccolor=#FFAD54\u003e350%\u003c/color\u003e\n·攻击时释放\u003ccolor=#FFAD54\u003e4\u003c/color\u003e道水波",
		"s_SkillInfoDesc": "进入战斗后，可自动升至2星\n并获得：水波伤害增加至攻击的\u003ccolor=#FFAD54\u003e154%\u003c/color\u003e\n海浪伤害增加至攻击的\u003ccolor=#FFAD54\u003e350%\u003c/color\u003e\n攻击时释放\u003ccolor=#FFAD54\u003e4\u003c/color\u003e道水波",
		"s_SkillName": "血脉觉醒"
	},
	{
		"i_Id": 73,
		"i_SkillId": 7,
		"i_SkillLevel": 3,
		"i_effectType": 0,
		"ill_effect": [
			[
				0
			]
		],
		"ill_effectcondition": [
			[
				0
			]
		],
		"s_ItemIcon": "awake_hero_1",
		"s_SkillDesc": "·水波伤害增加至攻击的\u003ccolor=#FFAD54\u003e176%\u003c/color\u003e\n·海浪伤害增加至攻击的\u003ccolor=#FFAD54\u003e400%\u003c/color\u003e\n·攻击时释放\u003ccolor=#FFAD54\u003e4\u003c/color\u003e道水波",
		"s_SkillInfoDesc": "进入战斗后，可自动升至3星\n战斗中获得：水波伤害增加至攻击的\u003ccolor=#FFAD54\u003e176%\u003c/color\u003e\n海浪伤害增加至攻击的\u003ccolor=#FFAD54\u003e400%\u003c/color\u003e\n攻击时释放\u003ccolor=#FFAD54\u003e4\u003c/color\u003e道水波",
		"s_SkillName": "血脉觉醒"
	},
	{
		"i_Id": 81,
		"i_SkillId": 8,
		"i_SkillLevel": 1,
		"i_effectType": 0,
		"ill_effect": [
			[
				0
			]
		],
		"ill_effectcondition": [
			[
				0
			]
		],
		"s_ItemIcon": "awake_hero_1",
		"s_SkillDesc": "·利爪旋刃伤害增加至攻击的\u003ccolor=#FFAD54\u003e360%\u003c/color\u003e\n·艾德曼旋风伤害增加至攻击的\u003ccolor=#FFAD54\u003e172%\u003c/color",
		"s_SkillInfoDesc": "战斗中，星级可突破5星\n并获得：利爪旋刃伤害增加至攻击的\u003ccolor=#FFAD54\u003e360%\u003c/color\u003e\n艾德曼旋风伤害增加至攻击的\u003ccolor=#FFAD54\u003e172%\u003c/color\u003e",
		"s_SkillName": "艾德曼金属"
	},
	{
		"i_Id": 82,
		"i_SkillId": 8,
		"i_SkillLevel": 2,
		"i_effectType": 0,
		"ill_effect": [
			[
				0
			]
		],
		"ill_effectcondition": [
			[
				0
			]
		],
		"s_ItemIcon": "awake_hero_1",
		"s_SkillDesc": "·利爪旋刃伤害增加至攻击的\u003ccolor=#FFAD54\u003e420%\u003c/color\u003e\n·艾德曼旋风伤害增加至攻击的\u003ccolor=#FFAD54\u003e201%\u003c/color\u003e\n·利爪旋刃释放\u003ccolor=#FFAD54\u003e4\u003c/color\u003e次",
		"s_SkillInfoDesc": "进入战斗后，可自动升至2星\n并获得：利爪旋刃伤害增加至攻击的\u003ccolor=#FFAD54\u003e420%\u003c/color\u003e\n艾德曼旋风伤害增加至攻击的\u003ccolor=#FFAD54\u003e201%\u003c/color\u003e\n利爪旋刃释放\u003ccolor=#FFAD54\u003e4\u003c/color\u003e次",
		"s_SkillName": "艾德曼金属"
	},
	{
		"i_Id": 83,
		"i_SkillId": 8,
		"i_SkillLevel": 3,
		"i_effectType": 0,
		"ill_effect": [
			[
				0
			]
		],
		"ill_effectcondition": [
			[
				0
			]
		],
		"s_ItemIcon": "awake_hero_1",
		"s_SkillDesc": "·利爪旋刃伤害增加至攻击的\u003ccolor=#FFAD54\u003e480%\u003c/color\u003e\n·艾德曼旋风伤害增加至攻击的\u003ccolor=#FFAD54\u003e230%\u003c/color\u003e\n·利爪旋刃释放\u003ccolor=#FFAD54\u003e4\u003c/color\u003e次",
		"s_SkillInfoDesc": "进入战斗后，可自动升至3星\n战斗中获得：利爪旋刃伤害增加至攻击的\u003ccolor=#FFAD54\u003e480%\u003c/color\u003e\n艾德曼旋风伤害增加至攻击的\u003ccolor=#FFAD54\u003e230%\u003c/color\u003e\n利爪旋刃释放\u003ccolor=#FFAD54\u003e4\u003c/color\u003e次",
		"s_SkillName": "艾德曼金属"
	},
	{
		"i_Id": 91,
		"i_SkillId": 9,
		"i_SkillLevel": 1,
		"i_effectType": 0,
		"ill_effect": [
			[
				0
			]
		],
		"ill_effectcondition": [
			[
				0
			]
		],
		"s_ItemIcon": "awake_hero_1",
		"s_SkillDesc": "·能量体伤害增加至攻击的\u003ccolor=#FFAD54\u003e90%\u003c/color\u003e\n·阿戈摩托之眼伤害增加至攻击的\u003ccolor=#FFAD54\u003e240%\u003c/color\u003e",
		"s_SkillInfoDesc": "战斗中，星级可突破5星\n并获得：能量体伤害增加至攻击的\u003ccolor=#FFAD54\u003e90%\u003c/color\u003e\n阿戈摩托之眼伤害增加至攻击的\u003ccolor=#FFAD54\u003e240%\u003c/color\u003e",
		"s_SkillName": "至尊法师"
	},
	{
		"i_Id": 92,
		"i_SkillId": 9,
		"i_SkillLevel": 2,
		"i_effectType": 0,
		"ill_effect": [
			[
				0
			]
		],
		"ill_effectcondition": [
			[
				0
			]
		],
		"s_ItemIcon": "awake_hero_1",
		"s_SkillDesc": "·能量体伤害增加至攻击的\u003ccolor=#FFAD54\u003e105%\u003c/color\u003e\n·阿戈摩托之眼伤害增加至攻击的\u003ccolor=#FFAD54\u003e280%\u003c/color\u003e\n·攻击时释放\u003ccolor=#FFAD54\u003e4\u003c/color\u003e个能量体",
		"s_SkillInfoDesc": "进入战斗后，可自动升至2星\n并获得：能量体伤害增加至攻击的\u003ccolor=#FFAD54\u003e105%\u003c/color\u003e\n阿戈摩托之眼伤害增加至攻击的\u003ccolor=#FFAD54\u003e280%\u003c/color\u003e\n攻击时释放\u003ccolor=#FFAD54\u003e4\u003c/color\u003e个能量体",
		"s_SkillName": "至尊法师"
	},
	{
		"i_Id": 93,
		"i_SkillId": 9,
		"i_SkillLevel": 3,
		"i_effectType": 0,
		"ill_effect": [
			[
				0
			]
		],
		"ill_effectcondition": [
			[
				0
			]
		],
		"s_ItemIcon": "awake_hero_1",
		"s_SkillDesc": "·能量体伤害增加至攻击的\u003ccolor=#FFAD54\u003e120%\u003c/color\u003e\n·阿戈摩托之眼伤害增加至攻击的\u003ccolor=#FFAD54\u003e320%\u003c/color\u003e\n·攻击时释放\u003ccolor=#FFAD54\u003e4\u003c/color\u003e个能量体",
		"s_SkillInfoDesc": "进入战斗后，可自动升至3星\n战斗中获得：能量体伤害增加至攻击的\u003ccolor=#FFAD54\u003e120%\u003c/color\u003e\n阿戈摩托之眼伤害增加至攻击的\u003ccolor=#FFAD54\u003e320%\u003c/color\u003e\n攻击时释放\u003ccolor=#FFAD54\u003e4\u003c/color\u003e个能量体",
		"s_SkillName": "至尊法师"
	},
	{
		"i_Id": 101,
		"i_SkillId": 10,
		"i_SkillLevel": 1,
		"i_effectType": 0,
		"ill_effect": [
			[
				0
			]
		],
		"ill_effectcondition": [
			[
				0
			]
		],
		"s_ItemIcon": "awake_hero_1",
		"s_SkillDesc": "·地面爆炸伤害增加至攻击的\u003ccolor=#FFAD54\u003e90%\u003c/color\u003e\n·汽车伤害增加至攻击的\u003ccolor=#FFAD54\u003e336%\u003c/color\u003e",
		"s_SkillInfoDesc": "战斗中，星级可突破5星\n并获得：地面爆炸伤害增加至攻击的\u003ccolor=#FFAD54\u003e90%\u003c/color\u003e\n汽车伤害增加至攻击的\u003ccolor=#FFAD54\u003e336%\u003c/color\u003e",
		"s_SkillName": "伽马能量"
	},
	{
		"i_Id": 102,
		"i_SkillId": 10,
		"i_SkillLevel": 2,
		"i_effectType": 0,
		"ill_effect": [
			[
				0
			]
		],
		"ill_effectcondition": [
			[
				0
			]
		],
		"s_ItemIcon": "awake_hero_1",
		"s_SkillDesc": "·地面爆炸伤害增加至攻击的\u003ccolor=#FFAD54\u003e105%\u003c/color\u003e\n·汽车伤害增加至攻击的\u003ccolor=#FFAD54\u003e392%\u003c/color\u003e\n·同时丢出\u003ccolor=#FFAD54\u003e6\u003c/color\u003e辆汽车",
		"s_SkillInfoDesc": "进入战斗后，可自动升至2星\n并获得：地面爆炸伤害增加至攻击的\u003ccolor=#FFAD54\u003e105%\u003c/color\u003e\n汽车伤害增加至攻击的\u003ccolor=#FFAD54\u003e392%\u003c/color\u003e\n同时丢出\u003ccolor=#FFAD54\u003e6\u003c/color\u003e辆汽车",
		"s_SkillName": "伽马能量"
	},
	{
		"i_Id": 103,
		"i_SkillId": 10,
		"i_SkillLevel": 3,
		"i_effectType": 0,
		"ill_effect": [
			[
				0
			]
		],
		"ill_effectcondition": [
			[
				0
			]
		],
		"s_ItemIcon": "awake_hero_1",
		"s_SkillDesc": "·地面爆炸伤害增加至攻击的\u003ccolor=#FFAD54\u003e120%\u003c/color\u003e\n·汽车伤害增加至攻击的\u003ccolor=#FFAD54\u003e448%\u003c/color\u003e\n·同时丢出\u003ccolor=#FFAD54\u003e6\u003c/color\u003e辆汽车",
		"s_SkillInfoDesc": "进入战斗后，可自动升至3星\n战斗中获得：地面爆炸伤害增加至攻击的\u003ccolor=#FFAD54\u003e120%\u003c/color\u003e\n汽车伤害增加至攻击的\u003ccolor=#FFAD54\u003e448%\u003c/color\u003e\n同时丢出\u003ccolor=#FFAD54\u003e6\u003c/color\u003e辆汽车",
		"s_SkillName": "伽马能量"
	},
	{
		"i_Id": 111,
		"i_SkillId": 11,
		"i_SkillLevel": 1,
		"i_effectType": 0,
		"ill_effect": [
			[
				0
			]
		],
		"ill_effectcondition": [
			[
				0
			]
		],
		"s_ItemIcon": "awake_hero_1",
		"s_SkillDesc": "·卡牌伤害增加至攻击的\u003ccolor=#FFAD54\u003e96%\u003c/color\u003e\n·强化卡牌伤害增加至攻击的\u003ccolor=#FFAD54\u003e108%\u003c/color\u003e",
		"s_SkillInfoDesc": "战斗中，星级可突破5星\n并获得：卡牌伤害增加至攻击的\u003ccolor=#FFAD54\u003e96%\u003c/color\u003e\n强化卡牌伤害增加至攻击的\u003ccolor=#FFAD54\u003e108%\u003c/color\u003e",
		"s_SkillName": "狂笑症"
	},
	{
		"i_Id": 112,
		"i_SkillId": 11,
		"i_SkillLevel": 2,
		"i_effectType": 0,
		"ill_effect": [
			[
				0
			]
		],
		"ill_effectcondition": [
			[
				0
			]
		],
		"s_ItemIcon": "awake_hero_1",
		"s_SkillDesc": "·卡牌伤害增加至攻击的\u003ccolor=#FFAD54\u003e112%\u003c/color\u003e\n·强化卡牌伤害增加至攻击的\u003ccolor=#FFAD54\u003e128%\u003c/color\u003e\n·攻击时获得\u003ccolor=#FFAD54\u003e20%\u003c/color\u003e攻速",
		"s_SkillInfoDesc": "进入战斗后，可自动升至2星\n并获得：卡牌伤害增加至攻击的\u003ccolor=#FFAD54\u003e112%\u003c/color\u003e\n强化卡牌伤害增加至攻击的\u003ccolor=#FFAD54\u003e128%\u003c/color\u003e\n攻击时获得\u003ccolor=#FFAD54\u003e20%\u003c/color\u003e攻速",
		"s_SkillName": "狂笑症"
	},
	{
		"i_Id": 113,
		"i_SkillId": 11,
		"i_SkillLevel": 3,
		"i_effectType": 0,
		"ill_effect": [
			[
				0
			]
		],
		"ill_effectcondition": [
			[
				0
			]
		],
		"s_ItemIcon": "awake_hero_1",
		"s_SkillDesc": "·卡牌伤害增加至攻击的\u003ccolor=#FFAD54\u003e126%\u003c/color\u003e\n·强化卡牌伤害增加至攻击的\u003ccolor=#FFAD54\u003e144%\u003c/color\u003e\n·攻击时获得\u003ccolor=#FFAD54\u003e20%\u003c/color\u003e攻速",
		"s_SkillInfoDesc": "进入战斗后，可自动升至3星\n战斗中获得：卡牌伤害增加至攻击的\u003ccolor=#FFAD54\u003e126%\u003c/color\u003e\n强化卡牌伤害增加至攻击的\u003ccolor=#FFAD54\u003e144%\u003c/color\u003e\n攻击时获得\u003ccolor=#FFAD54\u003e20%\u003c/color\u003e攻速",
		"s_SkillName": "狂笑症"
	},
	{
		"i_Id": 121,
		"i_SkillId": 12,
		"i_SkillLevel": 1,
		"i_effectType": 0,
		"ill_effect": [
			[
				0
			]
		],
		"ill_effectcondition": [
			[
				0
			]
		],
		"s_ItemIcon": "awake_hero_1",
		"s_SkillDesc": "·星月伤害增加至攻击的\u003ccolor=#FFAD54\u003e120%\u003c/color\u003e\n·月亮闪烁伤害增加至攻击的\u003ccolor=#FFAD54\u003e384%\u003c/color\u003e",
		"s_SkillInfoDesc": "战斗中，星级可突破5星\n并获得：星月伤害增加至攻击的\u003ccolor=#FFAD54\u003e120%\u003c/color\u003e\n月亮闪烁伤害增加至攻击的\u003ccolor=#FFAD54\u003e384%\u003c/color\u003e",
		"s_SkillName": "公主光辉"
	},
	{
		"i_Id": 122,
		"i_SkillId": 12,
		"i_SkillLevel": 2,
		"i_effectType": 0,
		"ill_effect": [
			[
				0
			]
		],
		"ill_effectcondition": [
			[
				0
			]
		],
		"s_ItemIcon": "awake_hero_1",
		"s_SkillDesc": "·星月伤害增加至攻击的\u003ccolor=#FFAD54\u003e140%\u003c/color\u003e\n·月亮闪烁伤害增加至攻击的\u003ccolor=#FFAD54\u003e448%\u003c/color\u003e\n·发射\u003ccolor=#FFAD54\u003e4\u003c/color\u003e个星月",
		"s_SkillInfoDesc": "进入战斗后，可自动升至2星\n并获得：星月伤害增加至攻击的\u003ccolor=#FFAD54\u003e140%\u003c/color\u003e\n月亮闪烁伤害增加至攻击的\u003ccolor=#FFAD54\u003e448%\u003c/color\u003e\n发射\u003ccolor=#FFAD54\u003e4\u003c/color\u003e个星月",
		"s_SkillName": "公主光辉"
	},
	{
		"i_Id": 123,
		"i_SkillId": 12,
		"i_SkillLevel": 3,
		"i_effectType": 0,
		"ill_effect": [
			[
				0
			]
		],
		"ill_effectcondition": [
			[
				0
			]
		],
		"s_ItemIcon": "awake_hero_1",
		"s_SkillDesc": "·星月伤害增加至攻击的\u003ccolor=#FFAD54\u003e160%\u003c/color\u003e\n·月亮闪烁伤害增加至攻击的\u003ccolor=#FFAD54\u003e512%\u003c/color\u003e\n·发射\u003ccolor=#FFAD54\u003e4\u003c/color\u003e个星月",
		"s_SkillInfoDesc": "进入战斗后，可自动升至3星\n战斗中获得：星月伤害增加至攻击的\u003ccolor=#FFAD54\u003e160%\u003c/color\u003e\n月亮闪烁伤害增加至攻击的\u003ccolor=#FFAD54\u003e512%\u003c/color\u003e\n发射\u003ccolor=#FFAD54\u003e4\u003c/color\u003e个星月",
		"s_SkillName": "公主光辉"
	},
	{
		"i_Id": 131,
		"i_SkillId": 13,
		"i_SkillLevel": 1,
		"i_effectType": 0,
		"ill_effect": [
			[
				0
			]
		],
		"ill_effectcondition": [
			[
				0
			]
		],
		"s_ItemIcon": "awake_hero_1",
		"s_SkillDesc": "·子弹伤害增加至攻击的\u003ccolor=#FFAD54\u003e77%\u003c/color\u003e\n·霰弹伤害增加至攻击的\u003ccolor=#FFAD54\u003e153%\u003c/color\u003e",
		"s_SkillInfoDesc": "战斗中，星级可突破5星\n并获得：子弹伤害增加至攻击的\u003ccolor=#FFAD54\u003e77%\u003c/color\u003e\n霰弹伤害增加至攻击的\u003ccolor=#FFAD54\u003e153%\u003c/color\u003e",
		"s_SkillName": "未来机器"
	},
	{
		"i_Id": 132,
		"i_SkillId": 13,
		"i_SkillLevel": 2,
		"i_effectType": 0,
		"ill_effect": [
			[
				0
			]
		],
		"ill_effectcondition": [
			[
				0
			]
		],
		"s_ItemIcon": "awake_hero_1",
		"s_SkillDesc": "·子弹伤害增加至攻击的\u003ccolor=#FFAD54\u003e89%\u003c/color\u003e\n·霰弹伤害增加至攻击的\u003ccolor=#FFAD54\u003e179%\u003c/color\u003e\n·攻击时获得\u003ccolor=#FFAD54\u003e20%\u003c/color\u003e攻速",
		"s_SkillInfoDesc": "进入战斗后，可自动升至2星\n并获得：子弹伤害增加至攻击的\u003ccolor=#FFAD54\u003e89%\u003c/color\u003e\n霰弹伤害增加至攻击的\u003ccolor=#FFAD54\u003e179%\u003c/color\u003e\n攻击时获得\u003ccolor=#FFAD54\u003e20%\u003c/color\u003e攻速",
		"s_SkillName": "未来机器"
	},
	{
		"i_Id": 133,
		"i_SkillId": 13,
		"i_SkillLevel": 3,
		"i_effectType": 0,
		"ill_effect": [
			[
				0
			]
		],
		"ill_effectcondition": [
			[
				0
			]
		],
		"s_ItemIcon": "awake_hero_1",
		"s_SkillDesc": "·子弹伤害增加至攻击的\u003ccolor=#FFAD54\u003e102%\u003c/color\u003e\n·霰弹伤害增加至攻击的\u003ccolor=#FFAD54\u003e204%\u003c/color\u003e\n·攻击时获得\u003ccolor=#FFAD54\u003e20%\u003c/color\u003e攻速",
		"s_SkillInfoDesc": "进入战斗后，可自动升至3星\n战斗中获得：子弹伤害增加至攻击的\u003ccolor=#FFAD54\u003e102%\u003c/color\u003e\n霰弹伤害增加至攻击的\u003ccolor=#FFAD54\u003e204%\u003c/color\u003e\n攻击时获得\u003ccolor=#FFAD54\u003e20%\u003c/color\u003e攻速",
		"s_SkillName": "未来机器"
	},
	{
		"i_Id": 141,
		"i_SkillId": 14,
		"i_SkillLevel": 1,
		"i_effectType": 0,
		"ill_effect": [
			[
				0
			]
		],
		"ill_effectcondition": [
			[
				0
			]
		],
		"s_ItemIcon": "awake_hero_1",
		"s_SkillDesc": "·冲刺伤害增加至攻击的\u003ccolor=#FFAD54\u003e360%\u003c/color\u003e\n·神速力伤害增加至攻击的\u003ccolor=#FFAD54\u003e103%\u003c/color\u003e",
		"s_SkillInfoDesc": "战斗中，星级可突破5星\n并获得：冲刺伤害增加至攻击的\u003ccolor=#FFAD54\u003e360%\u003c/color\u003e\n神速力伤害增加至攻击的\u003ccolor=#FFAD54\u003e103%\u003c/color\u003e",
		"s_SkillName": "神速力"
	},
	{
		"i_Id": 142,
		"i_SkillId": 14,
		"i_SkillLevel": 2,
		"i_effectType": 0,
		"ill_effect": [
			[
				0
			]
		],
		"ill_effectcondition": [
			[
				0
			]
		],
		"s_ItemIcon": "awake_hero_1",
		"s_SkillDesc": "·冲刺伤害增加至攻击的\u003ccolor=#FFAD54\u003e420%\u003c/color\u003e\n·神速力伤害增加至攻击的\u003ccolor=#FFAD54\u003e120%\u003c/color\u003e\n·冲刺\u003ccolor=#FFAD54\u003e4\u003c/color\u003e次",
		"s_SkillInfoDesc": "进入战斗后，可自动升至2星\n并获得：一闪伤害增加至攻击的\u003ccolor=#FFAD54\u003e420%\u003c/color\u003e\n神速力伤害增加至攻击的\u003ccolor=#FFAD54\u003e120%\u003c/color\u003e\n冲刺\u003ccolor=#FFAD54\u003e4\u003c/color\u003e次",
		"s_SkillName": "神速力"
	},
	{
		"i_Id": 143,
		"i_SkillId": 14,
		"i_SkillLevel": 3,
		"i_effectType": 0,
		"ill_effect": [
			[
				0
			]
		],
		"ill_effectcondition": [
			[
				0
			]
		],
		"s_ItemIcon": "awake_hero_1",
		"s_SkillDesc": "·冲刺伤害增加至攻击的\u003ccolor=#FFAD54\u003e480%\u003c/color\u003e\n·神速力伤害增加至攻击的\u003ccolor=#FFAD54\u003e137%\u003c/color\u003e\n·冲刺\u003ccolor=#FFAD54\u003e4\u003c/color\u003e次",
		"s_SkillInfoDesc": "进入战斗后，可自动升至3星\n战斗中获得：一闪伤害增加至攻击的\u003ccolor=#FFAD54\u003e480%\u003c/color\u003e\n神速力伤害增加至攻击的\u003ccolor=#FFAD54\u003e137%\u003c/color\u003e\n冲刺\u003ccolor=#FFAD54\u003e4\u003c/color\u003e次",
		"s_SkillName": "神速力"
	},
	{
		"i_Id": 151,
		"i_SkillId": 15,
		"i_SkillLevel": 1,
		"i_effectType": 0,
		"ill_effect": [
			[
				0
			]
		],
		"ill_effectcondition": [
			[
				0
			]
		],
		"s_ItemIcon": "awake_hero_1",
		"s_SkillDesc": "·穿透箭伤害增加至攻击的\u003ccolor=#FFAD54\u003e66%\u003c/color\u003e\n·爆炸箭伤害增加至攻击的\u003ccolor=#FFAD54\u003e136%\u003c/color\u003e",
		"s_SkillInfoDesc": "战斗中，星级可突破5星\n并获得：穿透箭伤害增加至攻击的\u003ccolor=#FFAD54\u003e66%\u003c/color\u003e\n爆炸箭伤害增加至攻击的\u003ccolor=#FFAD54\u003e136%\u003c/color\u003e",
		"s_SkillName": "箭无虚发"
	},
	{
		"i_Id": 152,
		"i_SkillId": 15,
		"i_SkillLevel": 2,
		"i_effectType": 0,
		"ill_effect": [
			[
				0
			]
		],
		"ill_effectcondition": [
			[
				0
			]
		],
		"s_ItemIcon": "awake_hero_1",
		"s_SkillDesc": "·穿透箭伤害增加至攻击的\u003ccolor=#FFAD54\u003e77%\u003c/color\u003e\n·爆炸箭伤害增加至攻击的\u003ccolor=#FFAD54\u003e159%\u003c/color\u003e\n·攻击时获得\u003ccolor=#FFAD54\u003e20%\u003c/color\u003e攻速",
		"s_SkillInfoDesc": "进入战斗后，可自动升至2星\n并获得：穿透箭伤害增加至攻击的\u003ccolor=#FFAD54\u003e77%\u003c/color\u003e\n爆炸箭伤害增加至攻击的\u003ccolor=#FFAD54\u003e159%\u003c/color\u003e\n攻击时获得\u003ccolor=#FFAD54\u003e20%\u003c/color\u003e攻速",
		"s_SkillName": "箭无虚发"
	},
	{
		"i_Id": 153,
		"i_SkillId": 15,
		"i_SkillLevel": 3,
		"i_effectType": 0,
		"ill_effect": [
			[
				0
			]
		],
		"ill_effectcondition": [
			[
				0
			]
		],
		"s_ItemIcon": "awake_hero_1",
		"s_SkillDesc": "·穿透箭伤害增加至攻击的\u003ccolor=#FFAD54\u003e88%\u003c/color\u003e\n·爆炸箭伤害增加至攻击的\u003ccolor=#FFAD54\u003e182%\u003c/color\u003e\n·攻击时获得\u003ccolor=#FFAD54\u003e20%\u003c/color\u003e攻速",
		"s_SkillInfoDesc": "进入战斗后，可自动升至3星\n战斗中获得：穿透箭伤害增加至攻击的\u003ccolor=#FFAD54\u003e88%\u003c/color\u003e\n爆炸箭伤害增加至攻击的\u003ccolor=#FFAD54\u003e182%\u003c/color\u003e\n攻击时获得\u003ccolor=#FFAD54\u003e20%\u003c/color\u003e攻速",
		"s_SkillName": "箭无虚发"
	},
	{
		"i_Id": 161,
		"i_SkillId": 16,
		"i_SkillLevel": 1,
		"i_effectType": 0,
		"ill_effect": [
			[
				0
			]
		],
		"ill_effectcondition": [
			[
				0
			]
		],
		"s_ItemIcon": "awake_hero_1",
		"s_SkillDesc": "·炮弹伤害增加至攻击的\u003ccolor=#FFAD54\u003e120%\u003c/color\u003e\n·触手伤害增加至攻击的\u003ccolor=#FFAD54\u003e360%\u003c/color\u003e",
		"s_SkillInfoDesc": "战斗中，星级可突破5星\n并获得：炮弹伤害增加至攻击的\u003ccolor=#FFAD54\u003e120%\u003c/color\u003e\n触手伤害增加至攻击的\u003ccolor=#FFAD54\u003e360%\u003c/color\u003e",
		"s_SkillName": "黑珍珠号"
	},
	{
		"i_Id": 162,
		"i_SkillId": 16,
		"i_SkillLevel": 2,
		"i_effectType": 0,
		"ill_effect": [
			[
				0
			]
		],
		"ill_effectcondition": [
			[
				0
			]
		],
		"s_ItemIcon": "awake_hero_1",
		"s_SkillDesc": "·炮弹伤害增加至攻击的\u003ccolor=#FFAD54\u003e140%\u003c/color\u003e\n·触手伤害增加至攻击的\u003ccolor=#FFAD54\u003e420%\u003c/color\u003e\n·触手数量\u003ccolor=#FFAD54\u003e+3\u003c/color\u003e",
		"s_SkillInfoDesc": "进入战斗后，可自动升至2星\n并获得：炮弹伤害增加至攻击的\u003ccolor=#FFAD54\u003e140%\u003c/color\u003e\n触手伤害增加至攻击的\u003ccolor=#FFAD54\u003e420%\u003c/color\u003e触手数量\u003ccolor=#FFAD54\u003e+3\u003c/color\u003e",
		"s_SkillName": "黑珍珠号"
	},
	{
		"i_Id": 163,
		"i_SkillId": 16,
		"i_SkillLevel": 3,
		"i_effectType": 0,
		"ill_effect": [
			[
				0
			]
		],
		"ill_effectcondition": [
			[
				0
			]
		],
		"s_ItemIcon": "awake_hero_1",
		"s_SkillDesc": "·炮弹伤害增加至攻击的\u003ccolor=#FFAD54\u003e160%\u003c/color\u003e\n·触手伤害增加至攻击的\u003ccolor=#FFAD54\u003e480%\u003c/color\u003e\n·触手数量\u003ccolor=#FFAD54\u003e+3\u003c/color\u003e",
		"s_SkillInfoDesc": "进入战斗后，可自动升至3星\n战斗中获得：炮弹伤害增加至攻击的\u003ccolor=#FFAD54\u003e160%\u003c/color\u003e\n触手伤害增加至攻击的\u003ccolor=#FFAD54\u003e480%\u003c/color\u003e\n触手数量\u003ccolor=#FFAD54\u003e+3\u003c/color\u003e",
		"s_SkillName": "黑珍珠号"
	},
	{
		"i_Id": 171,
		"i_SkillId": 17,
		"i_SkillLevel": 1,
		"i_effectType": 0,
		"ill_effect": [
			[
				0
			]
		],
		"ill_effectcondition": [
			[
				0
			]
		],
		"s_ItemIcon": "awake_hero_1",
		"s_SkillDesc": "·冰幔撞击伤害增加至攻击的\u003ccolor=#FFAD54\u003e360%\u003c/color\u003e\n·冰晶爆炸伤害增加至攻击的\u003ccolor=#FFAD54\u003e168%\u003c/color\u003e",
		"s_SkillInfoDesc": "战斗中，星级可突破5星\n并获得：冰幔撞击伤害增加至攻击的\u003ccolor=#FFAD54\u003e360%\u003c/color\u003e\n冰晶爆炸伤害增加至攻击的\u003ccolor=#FFAD54\u003e168%\u003c/color\u003e",
		"s_SkillName": "深度冻结"
	},
	{
		"i_Id": 172,
		"i_SkillId": 17,
		"i_SkillLevel": 2,
		"i_effectType": 0,
		"ill_effect": [
			[
				0
			]
		],
		"ill_effectcondition": [
			[
				0
			]
		],
		"s_ItemIcon": "awake_hero_1",
		"s_SkillDesc": "·冰幔撞击伤害增加至攻击的\u003ccolor=#FFAD54\u003e420%\u003c/color\u003e\n·冰晶爆炸伤害增加至攻击的\u003ccolor=#FFAD54\u003e196%\u003c/color\u003e\n·冰幔撞击冲刺\u003ccolor=#FFAD54\u003e4\u003c/color\u003e次",
		"s_SkillInfoDesc": "进入战斗后，可自动升至2星\n并获得：冰幔撞击伤害增加至攻击的\u003ccolor=#FFAD54\u003e420%\u003c/color\u003e\n冰晶爆炸增加至攻击的\u003ccolor=#FFAD54\u003e196%\u003c/color\u003e\n冰幔撞击冲刺\u003ccolor=#FFAD54\u003e4\u003c/color\u003e次",
		"s_SkillName": "深度冻结"
	},
	{
		"i_Id": 173,
		"i_SkillId": 17,
		"i_SkillLevel": 3,
		"i_effectType": 0,
		"ill_effect": [
			[
				0
			]
		],
		"ill_effectcondition": [
			[
				0
			]
		],
		"s_ItemIcon": "awake_hero_1",
		"s_SkillDesc": "·冰幔撞击伤害增加至攻击的\u003ccolor=#FFAD54\u003e480%\u003c/color\u003e\n·冰晶爆炸伤害增加至攻击的\u003ccolor=#FFAD54\u003e224%\u003c/color\u003e\n·冰幔撞击冲刺\u003ccolor=#FFAD54\u003e4\u003c/color\u003e次",
		"s_SkillInfoDesc": "进入战斗后，可自动升至3星\n战斗中获得：冰幔撞击伤害增加至攻击的\u003ccolor=#FFAD54\u003e480%\u003c/color\u003e\n冰晶爆炸伤害增加至攻击的\u003ccolor=#FFAD54\u003e224%\u003c/color\u003e",
		"s_SkillName": "深度冻结"
	},
	{
		"i_Id": 181,
		"i_SkillId": 18,
		"i_SkillLevel": 1,
		"i_effectType": 0,
		"ill_effect": [
			[
				0
			]
		],
		"ill_effectcondition": [
			[
				0
			]
		],
		"s_ItemIcon": "awake_hero_1",
		"s_SkillDesc": "·子弹伤害增加至攻击的\u003ccolor=#FFAD54\u003e93%\u003c/color\u003e\n·邪恶飞弹伤害增加至攻击的\u003ccolor=#FFAD54\u003e144%\u003c/color\u003e",
		"s_SkillInfoDesc": "战斗中，星级可突破5星\n并获得：子弹伤害增加至攻击的\u003ccolor=#FFAD54\u003e93%\u003c/color\u003e\n邪恶飞弹伤害增加至攻击的\u003ccolor=#FFAD54\u003e144%\u003c/color\u003e",
		"s_SkillName": "罪恶快感"
	},
	{
		"i_Id": 182,
		"i_SkillId": 18,
		"i_SkillLevel": 2,
		"i_effectType": 0,
		"ill_effect": [
			[
				0
			]
		],
		"ill_effectcondition": [
			[
				0
			]
		],
		"s_ItemIcon": "awake_hero_1",
		"s_SkillDesc": "·子弹伤害增加至攻击的\u003ccolor=#FFAD54\u003e110%\u003c/color\u003e\n·邪恶飞弹伤害增加至攻击的\u003ccolor=#FFAD54\u003e168%\u003c/color\u003e\n·攻击时获得\u003ccolor=#FFAD54\u003e20%\u003c/color\u003e攻速",
		"s_SkillInfoDesc": "进入战斗后，可自动升至2星\n并获得：子弹伤害增加至攻击的\u003ccolor=#FFAD54\u003e110%\u003c/color\u003e\n邪恶飞弹伤害增加至攻击的\u003ccolor=#FFAD54\u003e168%\u003c/color\u003e\n攻击时获得\u003ccolor=#FFAD54\u003e20%\u003c/color\u003e攻速",
		"s_SkillName": "罪恶快感"
	},
	{
		"i_Id": 183,
		"i_SkillId": 18,
		"i_SkillLevel": 3,
		"i_effectType": 0,
		"ill_effect": [
			[
				0
			]
		],
		"ill_effectcondition": [
			[
				0
			]
		],
		"s_ItemIcon": "awake_hero_1",
		"s_SkillDesc": "·子弹伤害增加至攻击的\u003ccolor=#FFAD54\u003e124%\u003c/color\u003e\n·邪恶飞弹伤害增加至攻击的\u003ccolor=#FFAD54\u003e192%\u003c/color\u003e\n·攻击时获得\u003ccolor=#FFAD54\u003e20%\u003c/color\u003e攻速",
		"s_SkillInfoDesc": "进入战斗后，可自动升至3星\n战斗中获得：子弹伤害增加至攻击的\u003ccolor=#FFAD54\u003e124%\u003c/color\u003e\n邪恶飞弹伤害增加至攻击的\u003ccolor=#FFAD54\u003e192%\u003c/color\u003e\n攻击时获得\u003ccolor=#FFAD54\u003e20%\u003c/color\u003e攻速",
		"s_SkillName": "罪恶快感"
	},
	{
		"i_Id": 191,
		"i_SkillId": 19,
		"i_SkillLevel": 1,
		"i_effectType": 0,
		"ill_effect": [
			[
				0
			]
		],
		"ill_effectcondition": [
			[
				0
			]
		],
		"s_ItemIcon": "awake_hero_1",
		"s_SkillDesc": "·贰号机伤害增加至攻击的\u003ccolor=#FFAD54\u003e360%\u003c/color\u003e\n·弑神领域伤害增加至攻击的\u003ccolor=#FFAD54\u003e86%\u003c/color\u003e",
		"s_SkillInfoDesc": "战斗中，星级可突破5星\n并获得：贰号机伤害增加至攻击的\u003ccolor=#FFAD54\u003e360%\u003c/color\u003e\n弑神领域伤害增加至攻击的\u003ccolor=#FFAD54\u003e86%\u003c/color\u003e",
		"s_SkillName": "驾驶天才"
	},
	{
		"i_Id": 192,
		"i_SkillId": 19,
		"i_SkillLevel": 2,
		"i_effectType": 0,
		"ill_effect": [
			[
				0
			]
		],
		"ill_effectcondition": [
			[
				0
			]
		],
		"s_ItemIcon": "awake_hero_1",
		"s_SkillDesc": "·贰号机伤害增加至攻击的\u003ccolor=#FFAD54\u003e420%\u003c/color\u003e\n·弑神领域伤害增加至攻击的\u003ccolor=#FFAD54\u003e100%\u003c/color\u003e\n·攻击时召唤\u003ccolor=#FFAD54\u003e4\u003c/color\u003e个贰号机",
		"s_SkillInfoDesc": "进入战斗后，可自动升至2星\n并获得：贰号机伤害增加至攻击的\u003ccolor=#FFAD54\u003e420%\u003c/color\u003e\n弑神领域伤害增加至攻击的\u003ccolor=#FFAD54\u003e100%\u003c/color\u003e\n攻击时召唤\u003ccolor=#FFAD54\u003e4\u003c/color\u003e个贰号机",
		"s_SkillName": "驾驶天才"
	},
	{
		"i_Id": 193,
		"i_SkillId": 19,
		"i_SkillLevel": 3,
		"i_effectType": 0,
		"ill_effect": [
			[
				0
			]
		],
		"ill_effectcondition": [
			[
				0
			]
		],
		"s_ItemIcon": "awake_hero_1",
		"s_SkillDesc": "·贰号机伤害增加至攻击的\u003ccolor=#FFAD54\u003e480%\u003c/color\u003e\n·弑神领域伤害增加至攻击的\u003ccolor=#FFAD54\u003e115%\u003c/color\u003e\n·攻击时召唤\u003ccolor=#FFAD54\u003e4\u003c/color\u003e个贰号机",
		"s_SkillInfoDesc": "进入战斗后，可自动升至3星\n战斗中获得：贰号机伤害增加至攻击的\u003ccolor=#FFAD54\u003e480%\u003c/color\u003e\n弑神领域伤害增加至攻击的\u003ccolor=#FFAD54\u003e115%\u003c/color\u003e\n攻击时召唤\u003ccolor=#FFAD54\u003e4\u003c/color\u003e个贰号机",
		"s_SkillName": "驾驶天才"
	},
	{
		"i_Id": 201,
		"i_SkillId": 20,
		"i_SkillLevel": 1,
		"i_effectType": 0,
		"ill_effect": [
			[
				0
			]
		],
		"ill_effectcondition": [
			[
				0
			]
		],
		"s_ItemIcon": "awake_hero_1",
		"s_SkillDesc": "·火焰放射伤害增加至攻击的\u003ccolor=#FFAD54\u003e120%\u003c/color\u003e\n·巨龙咆哮伤害增加至攻击的\u003ccolor=#FFAD54\u003e168%\u003c/color\u003e",
		"s_SkillInfoDesc": "战斗中，星级可突破5星\n并获得：火焰放射伤害增加至攻击的\u003ccolor=#FFAD54\u003e120%\u003c/color\u003e\n巨龙咆哮伤害增加至攻击的\u003ccolor=#FFAD54\u003e168%\u003c/color\u003e",
		"s_SkillName": "七国女王"
	},
	{
		"i_Id": 202,
		"i_SkillId": 20,
		"i_SkillLevel": 2,
		"i_effectType": 0,
		"ill_effect": [
			[
				0
			]
		],
		"ill_effectcondition": [
			[
				0
			]
		],
		"s_ItemIcon": "awake_hero_1",
		"s_SkillDesc": "·火焰放射伤害增加至攻击的\u003ccolor=#FFAD54\u003e140%\u003c/color\u003e\n·巨龙咆哮伤害增加至攻击的\u003ccolor=#FFAD54\u003e196%\u003c/color\u003e\n·发射\u003ccolor=#FFAD54\u003e4\u003c/color\u003e个龙痰",
		"s_SkillInfoDesc": "进入战斗后，可自动升至2星\n并获得：火焰放射伤害增加至攻击的\u003ccolor=#FFAD54\u003e140%\u003c/color\u003e\n巨龙咆哮伤害增加至攻击的\u003ccolor=#FFAD54\u003e196%\u003c/color\u003e\n发射\u003ccolor=#FFAD54\u003e4\u003c/color\u003e个龙痰",
		"s_SkillName": "七国女王"
	},
	{
		"i_Id": 203,
		"i_SkillId": 20,
		"i_SkillLevel": 3,
		"i_effectType": 0,
		"ill_effect": [
			[
				0
			]
		],
		"ill_effectcondition": [
			[
				0
			]
		],
		"s_ItemIcon": "awake_hero_1",
		"s_SkillDesc": "·火焰放射伤害增加至攻击的\u003ccolor=#FFAD54\u003e160%\u003c/color\u003e\n·巨龙咆哮伤害增加至攻击的\u003ccolor=#FFAD54\u003e224%\u003c/color\u003e\n·发射\u003ccolor=#FFAD54\u003e4\u003c/color\u003e个龙痰",
		"s_SkillInfoDesc": "进入战斗后，可自动升至3星\n战斗中获得：火焰放射伤害增加至攻击的\u003ccolor=#FFAD54\u003e160%\u003c/color\u003e\n巨龙咆哮伤害增加至攻击的\u003ccolor=#FFAD54\u003e224%\u003c/color\u003e",
		"s_SkillName": "七国女王"
	},
	{
		"i_Id": 211,
		"i_SkillId": 21,
		"i_SkillLevel": 1,
		"i_effectType": 0,
		"ill_effect": [
			[
				0
			]
		],
		"ill_effectcondition": [
			[
				0
			]
		],
		"s_ItemIcon": "awake_hero_1",
		"s_SkillDesc": "·飓风能量伤害增加至攻击的\u003ccolor=#FFAD54\u003e114%\u003c/color\u003e\n·风暴来袭伤害增加至攻击的\u003ccolor=#FFAD54\u003e360%\u003c/color\u003e",
		"s_SkillInfoDesc": "战斗中，星级可突破5星\n并获得：飓风能量伤害增加至攻击的\u003ccolor=#FFAD54\u003e114%\u003c/color\u003e\n风暴来袭伤害增加至攻击的\u003ccolor=#FFAD54\u003e360%\u003c/color\u003e",
		"s_SkillName": "风暴感应"
	},
	{
		"i_Id": 212,
		"i_SkillId": 21,
		"i_SkillLevel": 2,
		"i_effectType": 0,
		"ill_effect": [
			[
				0
			]
		],
		"ill_effectcondition": [
			[
				0
			]
		],
		"s_ItemIcon": "awake_hero_1",
		"s_SkillDesc": "·飓风能量伤害增加至攻击的\u003ccolor=#FFAD54\u003e133%\u003c/color\u003e\n·风暴来袭伤害增加至攻击的\u003ccolor=#FFAD54\u003e420%\u003c/color\u003e\n·龙卷风释放数量\u003ccolor=#FFAD54\u003e+2\u003c/color\u003e",
		"s_SkillInfoDesc": "进入战斗后，可自动升至2星\n并获得：飓风能量伤害增加至攻击的\u003ccolor=#FFAD54\u003e133%\u003c/color\u003e\n风暴来袭伤害增加至攻击的\u003ccolor=#FFAD54\u003e420%\u003c/color\u003e\n龙卷风释放数量\u003ccolor=#FFAD54\u003e+2\u003c/color\u003e",
		"s_SkillName": "风暴感应"
	},
	{
		"i_Id": 213,
		"i_SkillId": 21,
		"i_SkillLevel": 3,
		"i_effectType": 0,
		"ill_effect": [
			[
				0
			]
		],
		"ill_effectcondition": [
			[
				0
			]
		],
		"s_ItemIcon": "awake_hero_1",
		"s_SkillDesc": "·飓风能量伤害增加至攻击的\u003ccolor=#FFAD54\u003e152%\u003c/color\u003e\n·风暴来袭伤害增加至攻击的\u003ccolor=#FFAD54\u003e480%\u003c/color\u003e\n·龙卷风释放数量\u003ccolor=#FFAD54\u003e+2\u003c/color\u003e",
		"s_SkillInfoDesc": "进入战斗后，可自动升至3星\n战斗中获得：飓风能量伤害增加至攻击的\u003ccolor=#FFAD54\u003e152%\u003c/color\u003e\n风暴来袭伤害增加至攻击的\u003ccolor=#FFAD54\u003e480%\u003c/color\u003e\n龙卷风释放数量\u003ccolor=#FFAD54\u003e+2\u003c/color\u003e",
		"s_SkillName": "风暴感应"
	},
	{
		"i_Id": 221,
		"i_SkillId": 22,
		"i_SkillLevel": 1,
		"i_effectType": 0,
		"ill_effect": [
			[
				0
			]
		],
		"ill_effectcondition": [
			[
				0
			]
		],
		"s_ItemIcon": "awake_hero_1",
		"s_SkillDesc": "·雷神之锤伤害增加至攻击的\u003ccolor=#FFAD54\u003e93%\u003c/color\u003e\n·雷神降临伤害增加至攻击的\u003ccolor=#FFAD54\u003e336%\u003c/color\u003e",
		"s_SkillInfoDesc": "战斗中，星级可突破5星\n并获得：雷神之锤伤害增加至攻击的\u003ccolor=#FFAD54\u003e93%\u003c/color\u003e\n雷神降临伤害增加至攻击的\u003ccolor=#FFAD54\u003e336%\u003c/color\u003e",
		"s_SkillName": "奥丁之力"
	},
	{
		"i_Id": 222,
		"i_SkillId": 22,
		"i_SkillLevel": 2,
		"i_effectType": 0,
		"ill_effect": [
			[
				0
			]
		],
		"ill_effectcondition": [
			[
				0
			]
		],
		"s_ItemIcon": "awake_hero_1",
		"s_SkillDesc": "·雷神之锤伤害增加至攻击的\u003ccolor=#FFAD54\u003e109%\u003c/color\u003e\n·雷神降临伤害增加至攻击的\u003ccolor=#FFAD54\u003e392%\u003c/color\u003e\n·雷神降临范围\u003ccolor=#FFAD54\u003e+20%\u003c/color\u003e",
		"s_SkillInfoDesc": "进入战斗后，可自动升至2星\n并获得：雷神之锤伤害增加至攻击的\u003ccolor=#FFAD54\u003e109%\u003c/color\u003e\n雷神降临伤害增加至攻击的\u003ccolor=#FFAD54\u003e392%\u003c/color\u003e\n雷神降临范围\u003ccolor=#FFAD54\u003e+20%\u003c/color\u003e",
		"s_SkillName": "奥丁之力"
	},
	{
		"i_Id": 223,
		"i_SkillId": 22,
		"i_SkillLevel": 3,
		"i_effectType": 0,
		"ill_effect": [
			[
				0
			]
		],
		"ill_effectcondition": [
			[
				0
			]
		],
		"s_ItemIcon": "awake_hero_1",
		"s_SkillDesc": "·雷神之锤伤害增加至攻击的\u003ccolor=#FFAD54\u003e124%\u003c/color\u003e\n·雷神降临伤害增加至攻击的\u003ccolor=#FFAD54\u003e448%\u003c/color\u003e\n·雷神降临范围\u003ccolor=#FFAD54\u003e+20%\u003c/color\u003e",
		"s_SkillInfoDesc": "进入战斗后，可自动升至3星\n战斗中获得：雷神之锤伤害增加至攻击的\u003ccolor=#FFAD54\u003e124%\u003c/color\u003e\n雷神降临伤害增加至攻击的\u003ccolor=#FFAD54\u003e448%\u003c/color\u003e\n雷神降临范围\u003ccolor=#FFAD54\u003e+20%\u003c/color\u003e",
		"s_SkillName": "奥丁之力"
	},
	{
		"i_Id": 231,
		"i_SkillId": 23,
		"i_SkillLevel": 1,
		"i_effectType": 0,
		"ill_effect": [
			[
				0
			]
		],
		"ill_effectcondition": [
			[
				0
			]
		],
		"s_ItemIcon": "awake_hero_1",
		"s_SkillDesc": "·气功波伤害增加至攻击的\u003ccolor=#FFAD54\u003e81%\u003c/color\u003e\n·超级气功波伤害增加至攻击的\u003ccolor=#FFAD54\u003e199%\u003c/color\u003e",
		"s_SkillInfoDesc": "战斗中，星级可突破5星\n并获得：气功波伤害增加至攻击的\u003ccolor=#FFAD54\u003e81%\u003c/color\u003e\n超级气功波伤害增加至攻击的\u003ccolor=#FFAD54\u003e199%\u003c/color\u003e",
		"s_SkillName": "战斗民族"
	},
	{
		"i_Id": 232,
		"i_SkillId": 23,
		"i_SkillLevel": 2,
		"i_effectType": 0,
		"ill_effect": [
			[
				0
			]
		],
		"ill_effectcondition": [
			[
				0
			]
		],
		"s_ItemIcon": "awake_hero_1",
		"s_SkillDesc": "·气功波伤害增加至攻击的\u003ccolor=#FFAD54\u003e95%\u003c/color\u003e\n·超级气功波伤害增加至攻击的\u003ccolor=#FFAD54\u003e232%\u003c/color\u003e\n·攻击时获得\u003ccolor=#FFAD54\u003e20%\u003c/color\u003e攻速",
		"s_SkillInfoDesc": "进入战斗后，可自动升至2星\n并获得：气功波伤害增加至攻击的\u003ccolor=#FFAD54\u003e95%\u003c/color\u003e\n超级气功波伤害增加至攻击的\u003ccolor=#FFAD54\u003e232%\u003c/color\u003e\n攻击时获得\u003ccolor=#FFAD54\u003e20%\u003c/color\u003e攻速",
		"s_SkillName": "战斗民族"
	},
	{
		"i_Id": 233,
		"i_SkillId": 23,
		"i_SkillLevel": 3,
		"i_effectType": 0,
		"ill_effect": [
			[
				0
			]
		],
		"ill_effectcondition": [
			[
				0
			]
		],
		"s_ItemIcon": "awake_hero_1",
		"s_SkillDesc": "·气功波伤害增加至攻击的\u003ccolor=#FFAD54\u003e108%\u003c/color\u003e\n·超级气功波伤害增加至攻击的\u003ccolor=#FFAD54\u003e265%\u003c/color\u003e\n·攻击时获得\u003ccolor=#FFAD54\u003e20%\u003c/color\u003e攻速",
		"s_SkillInfoDesc": "进入战斗后，可自动升至3星\n战斗中获得：气功波伤害增加至攻击的\u003ccolor=#FFAD54\u003e108%\u003c/color\u003e\n超级气功波伤害增加至攻击的\u003ccolor=#FFAD54\u003e265%\u003c/color\u003e\n攻击时获得\u003ccolor=#FFAD54\u003e20%\u003c/color\u003e攻速",
		"s_SkillName": "战斗民族"
	},
	{
		"i_Id": 241,
		"i_SkillId": 24,
		"i_SkillLevel": 1,
		"i_effectType": 0,
		"ill_effect": [
			[
				0
			]
		],
		"ill_effectcondition": [
			[
				0
			]
		],
		"s_ItemIcon": "awake_hero_1",
		"s_SkillDesc": "·蝙蝠伤害增加至攻击的\u003ccolor=#FFAD54\u003e96%\u003c/color\u003e\n·蝙蝠术伤害增加至攻击的\u003ccolor=#FFAD54\u003e230%\u003c/color\u003e",
		"s_SkillInfoDesc": "战斗中，星级可突破5星\n并获得：蝙蝠伤害增加至攻击的\u003ccolor=#FFAD54\u003e96%\u003c/color\u003e\n蝙蝠术伤害增加至攻击的\u003ccolor=#FFAD54\u003e230%\u003c/color\u003e",
		"s_SkillName": "血族恶魔"
	},
	{
		"i_Id": 242,
		"i_SkillId": 24,
		"i_SkillLevel": 2,
		"i_effectType": 0,
		"ill_effect": [
			[
				0
			]
		],
		"ill_effectcondition": [
			[
				0
			]
		],
		"s_ItemIcon": "awake_hero_1",
		"s_SkillDesc": "·蝙蝠伤害增加至攻击的\u003ccolor=#FFAD54\u003e112%\u003c/color\u003e\n·蝙蝠术伤害增加至攻击的\u003ccolor=#FFAD54\u003e268%\u003c/color\u003e\n·蝙蝠术额外治疗\u003ccolor=#FFAD54\u003e2\u003c/color\u003e名队友",
		"s_SkillInfoDesc": "进入战斗后，可自动升至2星\n并获得：蝙蝠伤害增加至攻击的\u003ccolor=#FFAD54\u003e112%\u003c/color\u003e\n蝙蝠术伤害增加至攻击的\u003ccolor=#FFAD54\u003e268%\u003c/color\u003e\n蝙蝠术额外治疗\u003ccolor=#FFAD54\u003e2\u003c/color\u003e名队友",
		"s_SkillName": "血族恶魔"
	},
	{
		"i_Id": 243,
		"i_SkillId": 24,
		"i_SkillLevel": 3,
		"i_effectType": 0,
		"ill_effect": [
			[
				0
			]
		],
		"ill_effectcondition": [
			[
				0
			]
		],
		"s_ItemIcon": "awake_hero_1",
		"s_SkillDesc": "·蝙蝠伤害增加至攻击的\u003ccolor=#FFAD54\u003e128%\u003c/color\u003e\n·蝙蝠术伤害增加至攻击的\u003ccolor=#FFAD54\u003e308%\u003c/color\u003e\n·蝙蝠术额外治疗\u003ccolor=#FFAD54\u003e2\u003c/color\u003e名队友",
		"s_SkillInfoDesc": "进入战斗后，可自动升至3星\n战斗中获得：蝙蝠伤害增加至攻击的\u003ccolor=#FFAD54\u003e128%\u003c/color\u003e\n蝙蝠术伤害增加至攻击的\u003ccolor=#FFAD54\u003e308%\u003c/color\u003e\n蝙蝠术额外治疗\u003ccolor=#FFAD54\u003e2\u003c/color\u003e名队友",
		"s_SkillName": "血族恶魔"
	},
	{
		"i_Id": 251,
		"i_SkillId": 25,
		"i_SkillLevel": 1,
		"i_effectType": 0,
		"ill_effect": [
			[
				0
			]
		],
		"ill_effectcondition": [
			[
				0
			]
		],
		"s_ItemIcon": "awake_hero_1",
		"s_SkillDesc": "·宝石伤害增加至攻击的\u003ccolor=#FFAD54\u003e144%\u003c/color\u003e\n·清除计划伤害增加至攻击的\u003ccolor=#FFAD54\u003e360%\u003c/color\u003e",
		"s_SkillInfoDesc": "战斗中，星级可突破5星\n并获得：宝石伤害增加至攻击的\u003ccolor=#FFAD54\u003e144%\u003c/color\u003e\n清除计划伤害增加至攻击的\u003ccolor=#FFAD54\u003e360%\u003c/color\u003e",
		"s_SkillName": "超级反派"
	},
	{
		"i_Id": 252,
		"i_SkillId": 25,
		"i_SkillLevel": 2,
		"i_effectType": 0,
		"ill_effect": [
			[
				0
			]
		],
		"ill_effectcondition": [
			[
				0
			]
		],
		"s_ItemIcon": "awake_hero_1",
		"s_SkillDesc": "·宝石伤害增加至攻击的\u003ccolor=#FFAD54\u003e168%\u003c/color\u003e\n·清除计划伤害增加至攻击的\u003ccolor=#FFAD54\u003e420%\u003c/color\u003e\n·清除计划范围\u003ccolor=#FFAD54\u003e+20%\u003c/color\u003e",
		"s_SkillInfoDesc": "进入战斗后，可自动升至2星\n并获得：宝石伤害增加至攻击的\u003ccolor=#FFAD54\u003e168%\u003c/color\u003e\n清除计划伤害增加至攻击的\u003ccolor=#FFAD54\u003e420%\u003c/color\u003e\n清除计划范围\u003ccolor=#FFAD54\u003e+20%\u003c/color\u003e",
		"s_SkillName": "超级反派"
	},
	{
		"i_Id": 253,
		"i_SkillId": 25,
		"i_SkillLevel": 3,
		"i_effectType": 0,
		"ill_effect": [
			[
				0
			]
		],
		"ill_effectcondition": [
			[
				0
			]
		],
		"s_ItemIcon": "awake_hero_1",
		"s_SkillDesc": "·宝石伤害增加至攻击的\u003ccolor=#FFAD54\u003e192%\u003c/color\u003e\n·清除计划伤害增加至攻击的\u003ccolor=#FFAD54\u003e480%\u003c/color\u003e\n·清除计划范围\u003ccolor=#FFAD54\u003e+20%\u003c/color\u003e",
		"s_SkillInfoDesc": "进入战斗后，可自动升至3星\n战斗中获得：宝石伤害增加至攻击的\u003ccolor=#FFAD54\u003e192%\u003c/color\u003e\n清除计划伤害增加至攻击的\u003ccolor=#FFAD54\u003e480%\u003c/color\u003e\n清除计划范围\u003ccolor=#FFAD54\u003e+20%\u003c/color\u003e",
		"s_SkillName": "超级反派"
	},
	{
		"i_Id": 261,
		"i_SkillId": 26,
		"i_SkillLevel": 1,
		"i_effectType": 0,
		"ill_effect": [
			[
				0
			]
		],
		"ill_effectcondition": [
			[
				0
			]
		],
		"s_ItemIcon": "awake_hero_1",
		"s_SkillDesc": "·邪恶爆弹伤害增加至攻击的\u003ccolor=#FFAD54\u003e132%\u003c/color\u003e\n·四分五裂伤害增加至攻击的\u003ccolor=#FFAD54\u003e360%\u003c/color\u003e",
		"s_SkillInfoDesc": "战斗中，星级可突破5星\n并获得：邪恶爆弹伤害增加至攻击的\u003ccolor=#FFAD54\u003e132%\u003c/color\u003e\n四分五裂伤害增加至攻击的\u003ccolor=#FFAD54\u003e360%\u003c/color\u003e",
		"s_SkillName": "邪恶基因"
	},
	{
		"i_Id": 262,
		"i_SkillId": 26,
		"i_SkillLevel": 2,
		"i_effectType": 0,
		"ill_effect": [
			[
				0
			]
		],
		"ill_effectcondition": [
			[
				0
			]
		],
		"s_ItemIcon": "awake_hero_1",
		"s_SkillDesc": "·邪恶爆弹伤害增加至攻击的\u003ccolor=#FFAD54\u003e154%\u003c/color\u003e\n·四分五裂伤害增加至攻击的\u003ccolor=#FFAD54\u003e420%\u003c/color\u003e\n·四分五裂分裂次数\u003ccolor=#FFAD54\u003e+4\u003c/color\u003e",
		"s_SkillInfoDesc": "进入战斗后，可自动升至2星\n并获得：邪恶爆弹伤害增加至攻击的\u003ccolor=#FFAD54\u003e154%\u003c/color\u003e\n四分五裂伤害增加至攻击的\u003ccolor=#FFAD54\u003e420%\u003c/color\u003e\n四分五裂分裂次数\u003ccolor=#FFAD54\u003e+4\u003c/color\u003e",
		"s_SkillName": "邪恶基因"
	},
	{
		"i_Id": 263,
		"i_SkillId": 26,
		"i_SkillLevel": 3,
		"i_effectType": 0,
		"ill_effect": [
			[
				0
			]
		],
		"ill_effectcondition": [
			[
				0
			]
		],
		"s_ItemIcon": "awake_hero_1",
		"s_SkillDesc": "·邪恶爆弹伤害增加至攻击的\u003ccolor=#FFAD54\u003e176%\u003c/color\u003e\n·四分五裂伤害增加至攻击的\u003ccolor=#FFAD54\u003e480%\u003c/color\u003e\n·四分五裂分裂次数\u003ccolor=#FFAD54\u003e+4\u003c/color\u003e",
		"s_SkillInfoDesc": "进入战斗后，可自动升至3星\n战斗中获得：邪恶爆弹伤害增加至攻击的\u003ccolor=#FFAD54\u003e176%\u003c/color\u003e\n四分五裂伤害增加至攻击的\u003ccolor=#FFAD54\u003e480%\u003c/color\u003e\n四分五裂分裂次数\u003ccolor=#FFAD54\u003e+4\u003c/color\u003e",
		"s_SkillName": "邪恶基因"
	},
	{
		"i_Id": 10011,
		"i_SkillId": 1001,
		"i_SkillLevel": 1,
		"i_effectType": 0,
		"ill_effect": [
			[
				0,
				1000
			],
			[
				0,
				1000
			],
			[
				0,
				1000
			]
		],
		"ill_effectcondition": [
			[
				0
			]
		],
		"s_ItemIcon": "",
		"s_SkillInfoDesc": "所有上阵英雄三属性+10%",
		"s_SkillName": "同心协力"
	},
	{
		"i_Id": 10012,
		"i_SkillId": 1001,
		"i_SkillLevel": 2,
		"i_effectType": 0,
		"ill_effect": [
			[
				0,
				1100
			],
			[
				0,
				1100
			],
			[
				0,
				1100
			]
		],
		"ill_effectcondition": [
			[
				0
			]
		],
		"s_ItemIcon": "",
		"s_SkillInfoDesc": "所有上阵英雄三属性+11%",
		"s_SkillName": "普通英雄被动"
	},
	{
		"i_Id": 10013,
		"i_SkillId": 1001,
		"i_SkillLevel": 3,
		"i_effectType": 0,
		"ill_effect": [
			[
				0,
				1200
			],
			[
				0,
				1200
			],
			[
				0,
				1200
			]
		],
		"ill_effectcondition": [
			[
				0
			]
		],
		"s_ItemIcon": "",
		"s_SkillInfoDesc": "所有上阵英雄三属性+12%",
		"s_SkillName": "普通英雄被动"
	},
	{
		"i_Id": 10014,
		"i_SkillId": 1001,
		"i_SkillLevel": 4,
		"i_effectType": 0,
		"ill_effect": [
			[
				0,
				1300
			],
			[
				0,
				1300
			],
			[
				0,
				1300
			]
		],
		"ill_effectcondition": [
			[
				0
			]
		],
		"s_ItemIcon": "",
		"s_SkillInfoDesc": "所有上阵英雄三属性+13%",
		"s_SkillName": "普通英雄被动"
	},
	{
		"i_Id": 10015,
		"i_SkillId": 1001,
		"i_SkillLevel": 5,
		"i_effectType": 0,
		"ill_effect": [
			[
				0,
				1400
			],
			[
				0,
				1400
			],
			[
				0,
				1400
			]
		],
		"ill_effectcondition": [
			[
				0
			]
		],
		"s_ItemIcon": "",
		"s_SkillInfoDesc": "所有上阵英雄三属性+14%",
		"s_SkillName": "普通英雄被动"
	},
	{
		"i_Id": 110101,
		"i_SkillId": 110101,
		"i_SkillLevel": 1,
		"s_ItemIcon": "icon_1",
		"s_SkillName": "测试技能1"
	},
	{
		"i_Id": 110102,
		"i_SkillId": 110102,
		"i_SkillLevel": 1,
		"s_ItemIcon": "icon_2",
		"s_SkillName": "测试技能2"
	},
	{
		"i_Id": 110103,
		"i_SkillId": 110103,
		"i_SkillLevel": 1,
		"s_ItemIcon": "icon_3",
		"s_SkillName": "测试技能3"
	},
	{
		"i_Id": 110104,
		"i_SkillId": 110104,
		"i_SkillLevel": 1,
		"s_ItemIcon": "icon_4",
		"s_SkillName": "测试技能4"
	},
	{
		"i_Id": 110201,
		"i_SkillId": 110201,
		"i_SkillLevel": 1,
		"s_ItemIcon": "icon_5",
		"s_SkillName": "测试技能5"
	},
	{
		"i_Id": 110202,
		"i_SkillId": 110202,
		"i_SkillLevel": 1,
		"s_ItemIcon": "icon_6",
		"s_SkillName": "测试技能6"
	},
	{
		"i_Id": 110203,
		"i_SkillId": 110203,
		"i_SkillLevel": 1,
		"s_ItemIcon": "icon_7",
		"s_SkillName": "测试技能7"
	},
	{
		"i_Id": 110204,
		"i_SkillId": 110204,
		"i_SkillLevel": 1,
		"s_ItemIcon": "icon_8",
		"s_SkillName": "测试技能8"
	},
	{
		"i_Id": 110301,
		"i_SkillId": 110301,
		"i_SkillLevel": 1,
		"s_ItemIcon": "icon_1",
		"s_SkillName": "测试技能9"
	},
	{
		"i_Id": 110302,
		"i_SkillId": 110302,
		"i_SkillLevel": 1,
		"s_ItemIcon": "icon_2",
		"s_SkillName": "测试技能10"
	},
	{
		"i_Id": 110303,
		"i_SkillId": 110303,
		"i_SkillLevel": 1,
		"s_ItemIcon": "icon_3",
		"s_SkillName": "测试技能11"
	},
	{
		"i_Id": 110304,
		"i_SkillId": 110304,
		"i_SkillLevel": 1,
		"s_ItemIcon": "icon_4",
		"s_SkillName": "测试技能12"
	},
	{
		"i_Id": 110305,
		"i_SkillId": 110305,
		"i_SkillLevel": 1,
		"s_ItemIcon": "icon_5",
		"s_SkillName": "测试技能13"
	},
	{
		"i_Id": 110401,
		"i_SkillId": 110401,
		"i_SkillLevel": 1,
		"s_ItemIcon": "icon_6",
		"s_SkillName": "测试技能14"
	},
	{
		"i_Id": 110402,
		"i_SkillId": 110402,
		"i_SkillLevel": 1,
		"s_ItemIcon": "icon_7",
		"s_SkillName": "测试技能15"
	},
	{
		"i_Id": 110403,
		"i_SkillId": 110403,
		"i_SkillLevel": 1,
		"s_ItemIcon": "icon_8",
		"s_SkillName": "测试技能16"
	},
	{
		"i_Id": 110404,
		"i_SkillId": 110404,
		"i_SkillLevel": 1,
		"s_ItemIcon": "icon_1",
		"s_SkillName": "测试技能17"
	},
	{
		"i_Id": 110405,
		"i_SkillId": 110405,
		"i_SkillLevel": 1,
		"s_ItemIcon": "icon_2",
		"s_SkillName": "测试技能18"
	},
	{
		"i_Id": 110501,
		"i_SkillId": 110501,
		"i_SkillLevel": 1,
		"s_ItemIcon": "icon_3",
		"s_SkillName": "测试技能19"
	},
	{
		"i_Id": 110502,
		"i_SkillId": 110502,
		"i_SkillLevel": 1,
		"s_ItemIcon": "icon_4",
		"s_SkillName": "测试技能20"
	},
	{
		"i_Id": 110503,
		"i_SkillId": 110503,
		"i_SkillLevel": 1,
		"s_ItemIcon": "icon_5",
		"s_SkillName": "测试技能21"
	},
	{
		"i_Id": 110504,
		"i_SkillId": 110504,
		"i_SkillLevel": 1,
		"s_ItemIcon": "icon_6",
		"s_SkillName": "测试技能22"
	},
	{
		"i_Id": 110505,
		"i_SkillId": 110505,
		"i_SkillLevel": 1,
		"s_ItemIcon": "icon_7",
		"s_SkillName": "测试技能23"
	},
	{
		"i_Id": 110506,
		"i_SkillId": 110506,
		"i_SkillLevel": 1,
		"s_ItemIcon": "icon_8",
		"s_SkillName": "测试技能24"
	},
	{
		"i_Id": 110601,
		"i_SkillId": 110601,
		"i_SkillLevel": 1,
		"s_ItemIcon": "icon_1",
		"s_SkillName": "测试技能25"
	},
	{
		"i_Id": 110602,
		"i_SkillId": 110602,
		"i_SkillLevel": 1,
		"s_ItemIcon": "icon_2",
		"s_SkillName": "测试技能26"
	},
	{
		"i_Id": 110603,
		"i_SkillId": 110603,
		"i_SkillLevel": 1,
		"s_ItemIcon": "icon_3",
		"s_SkillName": "测试技能27"
	},
	{
		"i_Id": 110604,
		"i_SkillId": 110604,
		"i_SkillLevel": 1,
		"s_ItemIcon": "icon_4",
		"s_SkillName": "测试技能28"
	},
	{
		"i_Id": 110605,
		"i_SkillId": 110605,
		"i_SkillLevel": 1,
		"s_ItemIcon": "icon_5",
		"s_SkillName": "测试技能29"
	},
	{
		"i_Id": 110606,
		"i_SkillId": 110606,
		"i_SkillLevel": 1,
		"s_ItemIcon": "icon_6",
		"s_SkillName": "测试技能30"
	},
	{
		"i_Id": 110607,
		"i_SkillId": 110607,
		"i_SkillLevel": 1,
		"s_ItemIcon": "icon_7",
		"s_SkillName": "测试技能31"
	},
	{
		"i_Id": 110608,
		"i_SkillId": 110608,
		"i_SkillLevel": 1,
		"s_ItemIcon": "icon_8",
		"s_SkillName": "测试技能32"
	},
	{
		"i_Id": 120101,
		"i_SkillId": 120101,
		"i_SkillLevel": 1,
		"s_ItemIcon": "icon_1",
		"s_SkillName": "测试技能33"
	},
	{
		"i_Id": 120102,
		"i_SkillId": 120102,
		"i_SkillLevel": 1,
		"s_ItemIcon": "icon_2",
		"s_SkillName": "测试技能34"
	},
	{
		"i_Id": 120103,
		"i_SkillId": 120103,
		"i_SkillLevel": 1,
		"s_ItemIcon": "icon_3",
		"s_SkillName": "测试技能35"
	},
	{
		"i_Id": 120104,
		"i_SkillId": 120104,
		"i_SkillLevel": 1,
		"s_ItemIcon": "icon_4",
		"s_SkillName": "测试技能36"
	},
	{
		"i_Id": 120201,
		"i_SkillId": 120201,
		"i_SkillLevel": 1,
		"s_ItemIcon": "icon_5",
		"s_SkillName": "测试技能37"
	},
	{
		"i_Id": 120202,
		"i_SkillId": 120202,
		"i_SkillLevel": 1,
		"s_ItemIcon": "icon_6",
		"s_SkillName": "测试技能38"
	},
	{
		"i_Id": 120203,
		"i_SkillId": 120203,
		"i_SkillLevel": 1,
		"s_ItemIcon": "icon_7",
		"s_SkillName": "测试技能39"
	},
	{
		"i_Id": 120204,
		"i_SkillId": 120204,
		"i_SkillLevel": 1,
		"s_ItemIcon": "icon_8",
		"s_SkillName": "测试技能40"
	},
	{
		"i_Id": 120301,
		"i_SkillId": 120301,
		"i_SkillLevel": 1,
		"s_ItemIcon": "icon_1",
		"s_SkillName": "测试技能41"
	},
	{
		"i_Id": 120302,
		"i_SkillId": 120302,
		"i_SkillLevel": 1,
		"s_ItemIcon": "icon_2",
		"s_SkillName": "测试技能42"
	},
	{
		"i_Id": 120303,
		"i_SkillId": 120303,
		"i_SkillLevel": 1,
		"s_ItemIcon": "icon_3",
		"s_SkillName": "测试技能43"
	},
	{
		"i_Id": 120304,
		"i_SkillId": 120304,
		"i_SkillLevel": 1,
		"s_ItemIcon": "icon_4",
		"s_SkillName": "测试技能44"
	},
	{
		"i_Id": 120305,
		"i_SkillId": 120305,
		"i_SkillLevel": 1,
		"s_ItemIcon": "icon_5",
		"s_SkillName": "测试技能45"
	},
	{
		"i_Id": 120401,
		"i_SkillId": 120401,
		"i_SkillLevel": 1,
		"s_ItemIcon": "icon_6",
		"s_SkillName": "测试技能46"
	},
	{
		"i_Id": 120402,
		"i_SkillId": 120402,
		"i_SkillLevel": 1,
		"s_ItemIcon": "icon_7",
		"s_SkillName": "测试技能47"
	},
	{
		"i_Id": 120403,
		"i_SkillId": 120403,
		"i_SkillLevel": 1,
		"s_ItemIcon": "icon_8",
		"s_SkillName": "测试技能48"
	},
	{
		"i_Id": 120404,
		"i_SkillId": 120404,
		"i_SkillLevel": 1,
		"s_ItemIcon": "icon_1",
		"s_SkillName": "测试技能49"
	},
	{
		"i_Id": 120405,
		"i_SkillId": 120405,
		"i_SkillLevel": 1,
		"s_ItemIcon": "icon_2",
		"s_SkillName": "测试技能50"
	},
	{
		"i_Id": 120501,
		"i_SkillId": 120501,
		"i_SkillLevel": 1,
		"s_ItemIcon": "icon_3",
		"s_SkillName": "测试技能51"
	},
	{
		"i_Id": 120502,
		"i_SkillId": 120502,
		"i_SkillLevel": 1,
		"s_ItemIcon": "icon_4",
		"s_SkillName": "测试技能52"
	},
	{
		"i_Id": 120503,
		"i_SkillId": 120503,
		"i_SkillLevel": 1,
		"s_ItemIcon": "icon_5",
		"s_SkillName": "测试技能53"
	},
	{
		"i_Id": 120504,
		"i_SkillId": 120504,
		"i_SkillLevel": 1,
		"s_ItemIcon": "icon_6",
		"s_SkillName": "测试技能54"
	},
	{
		"i_Id": 120505,
		"i_SkillId": 120505,
		"i_SkillLevel": 1,
		"s_ItemIcon": "icon_7",
		"s_SkillName": "测试技能55"
	},
	{
		"i_Id": 120506,
		"i_SkillId": 120506,
		"i_SkillLevel": 1,
		"s_ItemIcon": "icon_8",
		"s_SkillName": "测试技能56"
	},
	{
		"i_Id": 120601,
		"i_SkillId": 120601,
		"i_SkillLevel": 1,
		"s_ItemIcon": "icon_1",
		"s_SkillName": "测试技能57"
	},
	{
		"i_Id": 120602,
		"i_SkillId": 120602,
		"i_SkillLevel": 1,
		"s_ItemIcon": "icon_2",
		"s_SkillName": "测试技能58"
	},
	{
		"i_Id": 120603,
		"i_SkillId": 120603,
		"i_SkillLevel": 1,
		"s_ItemIcon": "icon_3",
		"s_SkillName": "测试技能59"
	},
	{
		"i_Id": 120604,
		"i_SkillId": 120604,
		"i_SkillLevel": 1,
		"s_ItemIcon": "icon_4",
		"s_SkillName": "测试技能60"
	},
	{
		"i_Id": 120605,
		"i_SkillId": 120605,
		"i_SkillLevel": 1,
		"s_ItemIcon": "icon_5",
		"s_SkillName": "测试技能61"
	},
	{
		"i_Id": 120606,
		"i_SkillId": 120606,
		"i_SkillLevel": 1,
		"s_ItemIcon": "icon_6",
		"s_SkillName": "测试技能62"
	},
	{
		"i_Id": 120607,
		"i_SkillId": 120607,
		"i_SkillLevel": 1,
		"s_ItemIcon": "icon_7",
		"s_SkillName": "测试技能63"
	},
	{
		"i_Id": 120608,
		"i_SkillId": 120608,
		"i_SkillLevel": 1,
		"s_ItemIcon": "icon_8",
		"s_SkillName": "测试技能64"
	},
	{
		"i_Id": 130101,
		"i_SkillId": 130101,
		"i_SkillLevel": 1,
		"s_ItemIcon": "icon_1",
		"s_SkillName": "测试技能65"
	},
	{
		"i_Id": 130102,
		"i_SkillId": 130102,
		"i_SkillLevel": 1,
		"s_ItemIcon": "icon_2",
		"s_SkillName": "测试技能66"
	},
	{
		"i_Id": 130103,
		"i_SkillId": 130103,
		"i_SkillLevel": 1,
		"s_ItemIcon": "icon_3",
		"s_SkillName": "测试技能67"
	},
	{
		"i_Id": 130104,
		"i_SkillId": 130104,
		"i_SkillLevel": 1,
		"s_ItemIcon": "icon_4",
		"s_SkillName": "测试技能68"
	},
	{
		"i_Id": 130201,
		"i_SkillId": 130201,
		"i_SkillLevel": 1,
		"s_ItemIcon": "icon_5",
		"s_SkillName": "测试技能69"
	},
	{
		"i_Id": 130202,
		"i_SkillId": 130202,
		"i_SkillLevel": 1,
		"s_ItemIcon": "icon_6",
		"s_SkillName": "测试技能70"
	},
	{
		"i_Id": 130203,
		"i_SkillId": 130203,
		"i_SkillLevel": 1,
		"s_ItemIcon": "icon_7",
		"s_SkillName": "测试技能71"
	},
	{
		"i_Id": 130204,
		"i_SkillId": 130204,
		"i_SkillLevel": 1,
		"s_ItemIcon": "icon_8",
		"s_SkillName": "测试技能72"
	},
	{
		"i_Id": 130301,
		"i_SkillId": 130301,
		"i_SkillLevel": 1,
		"s_ItemIcon": "icon_1",
		"s_SkillName": "测试技能73"
	},
	{
		"i_Id": 130302,
		"i_SkillId": 130302,
		"i_SkillLevel": 1,
		"s_ItemIcon": "icon_2",
		"s_SkillName": "测试技能74"
	},
	{
		"i_Id": 130303,
		"i_SkillId": 130303,
		"i_SkillLevel": 1,
		"s_ItemIcon": "icon_3",
		"s_SkillName": "测试技能75"
	},
	{
		"i_Id": 130304,
		"i_SkillId": 130304,
		"i_SkillLevel": 1,
		"s_ItemIcon": "icon_4",
		"s_SkillName": "测试技能76"
	},
	{
		"i_Id": 130305,
		"i_SkillId": 130305,
		"i_SkillLevel": 1,
		"s_ItemIcon": "icon_5",
		"s_SkillName": "测试技能77"
	},
	{
		"i_Id": 130401,
		"i_SkillId": 130401,
		"i_SkillLevel": 1,
		"s_ItemIcon": "icon_6",
		"s_SkillName": "测试技能78"
	},
	{
		"i_Id": 130402,
		"i_SkillId": 130402,
		"i_SkillLevel": 1,
		"s_ItemIcon": "icon_7",
		"s_SkillName": "测试技能79"
	},
	{
		"i_Id": 130403,
		"i_SkillId": 130403,
		"i_SkillLevel": 1,
		"s_ItemIcon": "icon_8",
		"s_SkillName": "测试技能80"
	},
	{
		"i_Id": 130404,
		"i_SkillId": 130404,
		"i_SkillLevel": 1,
		"s_ItemIcon": "icon_1",
		"s_SkillName": "测试技能81"
	},
	{
		"i_Id": 130405,
		"i_SkillId": 130405,
		"i_SkillLevel": 1,
		"s_ItemIcon": "icon_2",
		"s_SkillName": "测试技能82"
	},
	{
		"i_Id": 130501,
		"i_SkillId": 130501,
		"i_SkillLevel": 1,
		"s_ItemIcon": "icon_3",
		"s_SkillName": "测试技能83"
	},
	{
		"i_Id": 130502,
		"i_SkillId": 130502,
		"i_SkillLevel": 1,
		"s_ItemIcon": "icon_4",
		"s_SkillName": "测试技能84"
	},
	{
		"i_Id": 130503,
		"i_SkillId": 130503,
		"i_SkillLevel": 1,
		"s_ItemIcon": "icon_5",
		"s_SkillName": "测试技能85"
	},
	{
		"i_Id": 130504,
		"i_SkillId": 130504,
		"i_SkillLevel": 1,
		"s_ItemIcon": "icon_6",
		"s_SkillName": "测试技能86"
	},
	{
		"i_Id": 130505,
		"i_SkillId": 130505,
		"i_SkillLevel": 1,
		"s_ItemIcon": "icon_7",
		"s_SkillName": "测试技能87"
	},
	{
		"i_Id": 130506,
		"i_SkillId": 130506,
		"i_SkillLevel": 1,
		"s_ItemIcon": "icon_8",
		"s_SkillName": "测试技能88"
	},
	{
		"i_Id": 130601,
		"i_SkillId": 130601,
		"i_SkillLevel": 1,
		"s_ItemIcon": "icon_1",
		"s_SkillName": "测试技能89"
	},
	{
		"i_Id": 130602,
		"i_SkillId": 130602,
		"i_SkillLevel": 1,
		"s_ItemIcon": "icon_2",
		"s_SkillName": "测试技能90"
	},
	{
		"i_Id": 130603,
		"i_SkillId": 130603,
		"i_SkillLevel": 1,
		"s_ItemIcon": "icon_3",
		"s_SkillName": "测试技能91"
	},
	{
		"i_Id": 130604,
		"i_SkillId": 130604,
		"i_SkillLevel": 1,
		"s_ItemIcon": "icon_4",
		"s_SkillName": "测试技能92"
	},
	{
		"i_Id": 130605,
		"i_SkillId": 130605,
		"i_SkillLevel": 1,
		"s_ItemIcon": "icon_5",
		"s_SkillName": "测试技能93"
	},
	{
		"i_Id": 130606,
		"i_SkillId": 130606,
		"i_SkillLevel": 1,
		"s_ItemIcon": "icon_6",
		"s_SkillName": "测试技能94"
	},
	{
		"i_Id": 130607,
		"i_SkillId": 130607,
		"i_SkillLevel": 1,
		"s_ItemIcon": "icon_7",
		"s_SkillName": "测试技能95"
	},
	{
		"i_Id": 130608,
		"i_SkillId": 130608,
		"i_SkillLevel": 1,
		"s_ItemIcon": "icon_8",
		"s_SkillName": "测试技能96"
	},
	{
		"i_Id": 140101,
		"i_SkillId": 140101,
		"i_SkillLevel": 1,
		"s_ItemIcon": "icon_1",
		"s_SkillName": "测试技能97"
	},
	{
		"i_Id": 140102,
		"i_SkillId": 140102,
		"i_SkillLevel": 1,
		"s_ItemIcon": "icon_2",
		"s_SkillName": "测试技能98"
	},
	{
		"i_Id": 140103,
		"i_SkillId": 140103,
		"i_SkillLevel": 1,
		"s_ItemIcon": "icon_3",
		"s_SkillName": "测试技能99"
	},
	{
		"i_Id": 140104,
		"i_SkillId": 140104,
		"i_SkillLevel": 1,
		"s_ItemIcon": "icon_4",
		"s_SkillName": "测试技能100"
	},
	{
		"i_Id": 140201,
		"i_SkillId": 140201,
		"i_SkillLevel": 1,
		"s_ItemIcon": "icon_5",
		"s_SkillName": "测试技能101"
	},
	{
		"i_Id": 140202,
		"i_SkillId": 140202,
		"i_SkillLevel": 1,
		"s_ItemIcon": "icon_6",
		"s_SkillName": "测试技能102"
	},
	{
		"i_Id": 140203,
		"i_SkillId": 140203,
		"i_SkillLevel": 1,
		"s_ItemIcon": "icon_7",
		"s_SkillName": "测试技能103"
	},
	{
		"i_Id": 140204,
		"i_SkillId": 140204,
		"i_SkillLevel": 1,
		"s_ItemIcon": "icon_8",
		"s_SkillName": "测试技能104"
	},
	{
		"i_Id": 140301,
		"i_SkillId": 140301,
		"i_SkillLevel": 1,
		"s_ItemIcon": "icon_1",
		"s_SkillName": "测试技能105"
	},
	{
		"i_Id": 140302,
		"i_SkillId": 140302,
		"i_SkillLevel": 1,
		"s_ItemIcon": "icon_2",
		"s_SkillName": "测试技能106"
	},
	{
		"i_Id": 140303,
		"i_SkillId": 140303,
		"i_SkillLevel": 1,
		"s_ItemIcon": "icon_3",
		"s_SkillName": "测试技能107"
	},
	{
		"i_Id": 140304,
		"i_SkillId": 140304,
		"i_SkillLevel": 1,
		"s_ItemIcon": "icon_4",
		"s_SkillName": "测试技能108"
	},
	{
		"i_Id": 140305,
		"i_SkillId": 140305,
		"i_SkillLevel": 1,
		"s_ItemIcon": "icon_5",
		"s_SkillName": "测试技能109"
	},
	{
		"i_Id": 140401,
		"i_SkillId": 140401,
		"i_SkillLevel": 1,
		"s_ItemIcon": "icon_6",
		"s_SkillName": "测试技能110"
	},
	{
		"i_Id": 140402,
		"i_SkillId": 140402,
		"i_SkillLevel": 1,
		"s_ItemIcon": "icon_7",
		"s_SkillName": "测试技能111"
	},
	{
		"i_Id": 140403,
		"i_SkillId": 140403,
		"i_SkillLevel": 1,
		"s_ItemIcon": "icon_8",
		"s_SkillName": "测试技能112"
	},
	{
		"i_Id": 140404,
		"i_SkillId": 140404,
		"i_SkillLevel": 1,
		"s_ItemIcon": "icon_1",
		"s_SkillName": "测试技能113"
	},
	{
		"i_Id": 140405,
		"i_SkillId": 140405,
		"i_SkillLevel": 1,
		"s_ItemIcon": "icon_2",
		"s_SkillName": "测试技能114"
	},
	{
		"i_Id": 140501,
		"i_SkillId": 140501,
		"i_SkillLevel": 1,
		"s_ItemIcon": "icon_3",
		"s_SkillName": "测试技能115"
	},
	{
		"i_Id": 140502,
		"i_SkillId": 140502,
		"i_SkillLevel": 1,
		"s_ItemIcon": "icon_4",
		"s_SkillName": "测试技能116"
	},
	{
		"i_Id": 140503,
		"i_SkillId": 140503,
		"i_SkillLevel": 1,
		"s_ItemIcon": "icon_5",
		"s_SkillName": "测试技能117"
	},
	{
		"i_Id": 140504,
		"i_SkillId": 140504,
		"i_SkillLevel": 1,
		"s_ItemIcon": "icon_6",
		"s_SkillName": "测试技能118"
	},
	{
		"i_Id": 140505,
		"i_SkillId": 140505,
		"i_SkillLevel": 1,
		"s_ItemIcon": "icon_7",
		"s_SkillName": "测试技能119"
	},
	{
		"i_Id": 140506,
		"i_SkillId": 140506,
		"i_SkillLevel": 1,
		"s_ItemIcon": "icon_8",
		"s_SkillName": "测试技能120"
	},
	{
		"i_Id": 140601,
		"i_SkillId": 140601,
		"i_SkillLevel": 1,
		"s_ItemIcon": "icon_1",
		"s_SkillName": "测试技能121"
	},
	{
		"i_Id": 140602,
		"i_SkillId": 140602,
		"i_SkillLevel": 1,
		"s_ItemIcon": "icon_2",
		"s_SkillName": "测试技能122"
	},
	{
		"i_Id": 140603,
		"i_SkillId": 140603,
		"i_SkillLevel": 1,
		"s_ItemIcon": "icon_3",
		"s_SkillName": "测试技能123"
	},
	{
		"i_Id": 140604,
		"i_SkillId": 140604,
		"i_SkillLevel": 1,
		"s_ItemIcon": "icon_4",
		"s_SkillName": "测试技能124"
	},
	{
		"i_Id": 140605,
		"i_SkillId": 140605,
		"i_SkillLevel": 1,
		"s_ItemIcon": "icon_5",
		"s_SkillName": "测试技能125"
	},
	{
		"i_Id": 140606,
		"i_SkillId": 140606,
		"i_SkillLevel": 1,
		"s_ItemIcon": "icon_6",
		"s_SkillName": "测试技能126"
	},
	{
		"i_Id": 140607,
		"i_SkillId": 140607,
		"i_SkillLevel": 1,
		"s_ItemIcon": "icon_7",
		"s_SkillName": "测试技能127"
	},
	{
		"i_Id": 140608,
		"i_SkillId": 140608,
		"i_SkillLevel": 1,
		"s_ItemIcon": "icon_8",
		"s_SkillName": "测试技能128"
	},
	{
		"i_Id": 150101,
		"i_SkillId": 150101,
		"i_SkillLevel": 1,
		"s_ItemIcon": "icon_1",
		"s_SkillName": "测试技能129"
	},
	{
		"i_Id": 150102,
		"i_SkillId": 150102,
		"i_SkillLevel": 1,
		"s_ItemIcon": "icon_2",
		"s_SkillName": "测试技能130"
	},
	{
		"i_Id": 150103,
		"i_SkillId": 150103,
		"i_SkillLevel": 1,
		"s_ItemIcon": "icon_3",
		"s_SkillName": "测试技能131"
	},
	{
		"i_Id": 150104,
		"i_SkillId": 150104,
		"i_SkillLevel": 1,
		"s_ItemIcon": "icon_4",
		"s_SkillName": "测试技能132"
	},
	{
		"i_Id": 150201,
		"i_SkillId": 150201,
		"i_SkillLevel": 1,
		"s_ItemIcon": "icon_5",
		"s_SkillName": "测试技能133"
	},
	{
		"i_Id": 150202,
		"i_SkillId": 150202,
		"i_SkillLevel": 1,
		"s_ItemIcon": "icon_6",
		"s_SkillName": "测试技能134"
	},
	{
		"i_Id": 150203,
		"i_SkillId": 150203,
		"i_SkillLevel": 1,
		"s_ItemIcon": "icon_7",
		"s_SkillName": "测试技能135"
	},
	{
		"i_Id": 150204,
		"i_SkillId": 150204,
		"i_SkillLevel": 1,
		"s_ItemIcon": "icon_8",
		"s_SkillName": "测试技能136"
	},
	{
		"i_Id": 150301,
		"i_SkillId": 150301,
		"i_SkillLevel": 1,
		"s_ItemIcon": "icon_1",
		"s_SkillName": "测试技能137"
	},
	{
		"i_Id": 150302,
		"i_SkillId": 150302,
		"i_SkillLevel": 1,
		"s_ItemIcon": "icon_2",
		"s_SkillName": "测试技能138"
	},
	{
		"i_Id": 150303,
		"i_SkillId": 150303,
		"i_SkillLevel": 1,
		"s_ItemIcon": "icon_3",
		"s_SkillName": "测试技能139"
	},
	{
		"i_Id": 150304,
		"i_SkillId": 150304,
		"i_SkillLevel": 1,
		"s_ItemIcon": "icon_4",
		"s_SkillName": "测试技能140"
	},
	{
		"i_Id": 150305,
		"i_SkillId": 150305,
		"i_SkillLevel": 1,
		"s_ItemIcon": "icon_5",
		"s_SkillName": "测试技能141"
	},
	{
		"i_Id": 150401,
		"i_SkillId": 150401,
		"i_SkillLevel": 1,
		"s_ItemIcon": "icon_6",
		"s_SkillName": "测试技能142"
	},
	{
		"i_Id": 150402,
		"i_SkillId": 150402,
		"i_SkillLevel": 1,
		"s_ItemIcon": "icon_7",
		"s_SkillName": "测试技能143"
	},
	{
		"i_Id": 150403,
		"i_SkillId": 150403,
		"i_SkillLevel": 1,
		"s_ItemIcon": "icon_8",
		"s_SkillName": "测试技能144"
	},
	{
		"i_Id": 150404,
		"i_SkillId": 150404,
		"i_SkillLevel": 1,
		"s_ItemIcon": "icon_1",
		"s_SkillName": "测试技能145"
	},
	{
		"i_Id": 150405,
		"i_SkillId": 150405,
		"i_SkillLevel": 1,
		"s_ItemIcon": "icon_2",
		"s_SkillName": "测试技能146"
	},
	{
		"i_Id": 150501,
		"i_SkillId": 150501,
		"i_SkillLevel": 1,
		"s_ItemIcon": "icon_3",
		"s_SkillName": "测试技能147"
	},
	{
		"i_Id": 150502,
		"i_SkillId": 150502,
		"i_SkillLevel": 1,
		"s_ItemIcon": "icon_4",
		"s_SkillName": "测试技能148"
	},
	{
		"i_Id": 150503,
		"i_SkillId": 150503,
		"i_SkillLevel": 1,
		"s_ItemIcon": "icon_5",
		"s_SkillName": "测试技能149"
	},
	{
		"i_Id": 150504,
		"i_SkillId": 150504,
		"i_SkillLevel": 1,
		"s_ItemIcon": "icon_6",
		"s_SkillName": "测试技能150"
	},
	{
		"i_Id": 150505,
		"i_SkillId": 150505,
		"i_SkillLevel": 1,
		"s_ItemIcon": "icon_7",
		"s_SkillName": "测试技能151"
	},
	{
		"i_Id": 150506,
		"i_SkillId": 150506,
		"i_SkillLevel": 1,
		"s_ItemIcon": "icon_8",
		"s_SkillName": "测试技能152"
	},
	{
		"i_Id": 150601,
		"i_SkillId": 150601,
		"i_SkillLevel": 1,
		"s_ItemIcon": "icon_1",
		"s_SkillName": "测试技能153"
	},
	{
		"i_Id": 150602,
		"i_SkillId": 150602,
		"i_SkillLevel": 1,
		"s_ItemIcon": "icon_2",
		"s_SkillName": "测试技能154"
	},
	{
		"i_Id": 150603,
		"i_SkillId": 150603,
		"i_SkillLevel": 1,
		"s_ItemIcon": "icon_3",
		"s_SkillName": "测试技能155"
	},
	{
		"i_Id": 150604,
		"i_SkillId": 150604,
		"i_SkillLevel": 1,
		"s_ItemIcon": "icon_4",
		"s_SkillName": "测试技能156"
	},
	{
		"i_Id": 150605,
		"i_SkillId": 150605,
		"i_SkillLevel": 1,
		"s_ItemIcon": "icon_5",
		"s_SkillName": "测试技能157"
	},
	{
		"i_Id": 150606,
		"i_SkillId": 150606,
		"i_SkillLevel": 1,
		"s_ItemIcon": "icon_6",
		"s_SkillName": "测试技能158"
	},
	{
		"i_Id": 150607,
		"i_SkillId": 150607,
		"i_SkillLevel": 1,
		"s_ItemIcon": "icon_7",
		"s_SkillName": "测试技能159"
	},
	{
		"i_Id": 150608,
		"i_SkillId": 150608,
		"i_SkillLevel": 1,
		"s_ItemIcon": "icon_8",
		"s_SkillName": "测试技能160"
	},
	{
		"i_Id": 160101,
		"i_SkillId": 160101,
		"i_SkillLevel": 1,
		"s_ItemIcon": "icon_1",
		"s_SkillName": "测试技能161"
	},
	{
		"i_Id": 160102,
		"i_SkillId": 160102,
		"i_SkillLevel": 1,
		"s_ItemIcon": "icon_2",
		"s_SkillName": "测试技能162"
	},
	{
		"i_Id": 160103,
		"i_SkillId": 160103,
		"i_SkillLevel": 1,
		"s_ItemIcon": "icon_3",
		"s_SkillName": "测试技能163"
	},
	{
		"i_Id": 160104,
		"i_SkillId": 160104,
		"i_SkillLevel": 1,
		"s_ItemIcon": "icon_4",
		"s_SkillName": "测试技能164"
	},
	{
		"i_Id": 160201,
		"i_SkillId": 160201,
		"i_SkillLevel": 1,
		"s_ItemIcon": "icon_5",
		"s_SkillName": "测试技能165"
	},
	{
		"i_Id": 160202,
		"i_SkillId": 160202,
		"i_SkillLevel": 1,
		"s_ItemIcon": "icon_6",
		"s_SkillName": "测试技能166"
	},
	{
		"i_Id": 160203,
		"i_SkillId": 160203,
		"i_SkillLevel": 1,
		"s_ItemIcon": "icon_7",
		"s_SkillName": "测试技能167"
	},
	{
		"i_Id": 160204,
		"i_SkillId": 160204,
		"i_SkillLevel": 1,
		"s_ItemIcon": "icon_8",
		"s_SkillName": "测试技能168"
	},
	{
		"i_Id": 160301,
		"i_SkillId": 160301,
		"i_SkillLevel": 1,
		"s_ItemIcon": "icon_1",
		"s_SkillName": "测试技能169"
	},
	{
		"i_Id": 160302,
		"i_SkillId": 160302,
		"i_SkillLevel": 1,
		"s_ItemIcon": "icon_2",
		"s_SkillName": "测试技能170"
	},
	{
		"i_Id": 160303,
		"i_SkillId": 160303,
		"i_SkillLevel": 1,
		"s_ItemIcon": "icon_3",
		"s_SkillName": "测试技能171"
	},
	{
		"i_Id": 160304,
		"i_SkillId": 160304,
		"i_SkillLevel": 1,
		"s_ItemIcon": "icon_4",
		"s_SkillName": "测试技能172"
	},
	{
		"i_Id": 160305,
		"i_SkillId": 160305,
		"i_SkillLevel": 1,
		"s_ItemIcon": "icon_5",
		"s_SkillName": "测试技能173"
	},
	{
		"i_Id": 160401,
		"i_SkillId": 160401,
		"i_SkillLevel": 1,
		"s_ItemIcon": "icon_6",
		"s_SkillName": "测试技能174"
	},
	{
		"i_Id": 160402,
		"i_SkillId": 160402,
		"i_SkillLevel": 1,
		"s_ItemIcon": "icon_7",
		"s_SkillName": "测试技能175"
	},
	{
		"i_Id": 160403,
		"i_SkillId": 160403,
		"i_SkillLevel": 1,
		"s_ItemIcon": "icon_8",
		"s_SkillName": "测试技能176"
	},
	{
		"i_Id": 160404,
		"i_SkillId": 160404,
		"i_SkillLevel": 1,
		"s_ItemIcon": "icon_1",
		"s_SkillName": "测试技能177"
	},
	{
		"i_Id": 160405,
		"i_SkillId": 160405,
		"i_SkillLevel": 1,
		"s_ItemIcon": "icon_2",
		"s_SkillName": "测试技能178"
	},
	{
		"i_Id": 160501,
		"i_SkillId": 160501,
		"i_SkillLevel": 1,
		"s_ItemIcon": "icon_3",
		"s_SkillName": "测试技能179"
	},
	{
		"i_Id": 160502,
		"i_SkillId": 160502,
		"i_SkillLevel": 1,
		"s_ItemIcon": "icon_4",
		"s_SkillName": "测试技能180"
	},
	{
		"i_Id": 160503,
		"i_SkillId": 160503,
		"i_SkillLevel": 1,
		"s_ItemIcon": "icon_5",
		"s_SkillName": "测试技能181"
	},
	{
		"i_Id": 160504,
		"i_SkillId": 160504,
		"i_SkillLevel": 1,
		"s_ItemIcon": "icon_6",
		"s_SkillName": "测试技能182"
	},
	{
		"i_Id": 160505,
		"i_SkillId": 160505,
		"i_SkillLevel": 1,
		"s_ItemIcon": "icon_7",
		"s_SkillName": "测试技能183"
	},
	{
		"i_Id": 160506,
		"i_SkillId": 160506,
		"i_SkillLevel": 1,
		"s_ItemIcon": "icon_8",
		"s_SkillName": "测试技能184"
	},
	{
		"i_Id": 160601,
		"i_SkillId": 160601,
		"i_SkillLevel": 1,
		"s_ItemIcon": "icon_1",
		"s_SkillName": "测试技能185"
	},
	{
		"i_Id": 160602,
		"i_SkillId": 160602,
		"i_SkillLevel": 1,
		"s_ItemIcon": "icon_2",
		"s_SkillName": "测试技能186"
	},
	{
		"i_Id": 160603,
		"i_SkillId": 160603,
		"i_SkillLevel": 1,
		"s_ItemIcon": "icon_3",
		"s_SkillName": "测试技能187"
	},
	{
		"i_Id": 160604,
		"i_SkillId": 160604,
		"i_SkillLevel": 1,
		"s_ItemIcon": "icon_4",
		"s_SkillName": "测试技能188"
	},
	{
		"i_Id": 160605,
		"i_SkillId": 160605,
		"i_SkillLevel": 1,
		"s_ItemIcon": "icon_5",
		"s_SkillName": "测试技能189"
	},
	{
		"i_Id": 160606,
		"i_SkillId": 160606,
		"i_SkillLevel": 1,
		"s_ItemIcon": "icon_6",
		"s_SkillName": "测试技能190"
	},
	{
		"i_Id": 160607,
		"i_SkillId": 160607,
		"i_SkillLevel": 1,
		"s_ItemIcon": "icon_7",
		"s_SkillName": "测试技能191"
	},
	{
		"i_Id": 160608,
		"i_SkillId": 160608,
		"i_SkillLevel": 1,
		"s_ItemIcon": "icon_8",
		"s_SkillName": "测试技能192"
	},
	{
		"i_Id": 170101,
		"i_SkillId": 170101,
		"i_SkillLevel": 1,
		"s_ItemIcon": "icon_1",
		"s_SkillName": "测试技能193"
	},
	{
		"i_Id": 170102,
		"i_SkillId": 170102,
		"i_SkillLevel": 1,
		"s_ItemIcon": "icon_2",
		"s_SkillName": "测试技能194"
	},
	{
		"i_Id": 170103,
		"i_SkillId": 170103,
		"i_SkillLevel": 1,
		"s_ItemIcon": "icon_3",
		"s_SkillName": "测试技能195"
	},
	{
		"i_Id": 170104,
		"i_SkillId": 170104,
		"i_SkillLevel": 1,
		"s_ItemIcon": "icon_4",
		"s_SkillName": "测试技能196"
	},
	{
		"i_Id": 170201,
		"i_SkillId": 170201,
		"i_SkillLevel": 1,
		"s_ItemIcon": "icon_1",
		"s_SkillName": "测试技能197"
	},
	{
		"i_Id": 170202,
		"i_SkillId": 170202,
		"i_SkillLevel": 1,
		"s_ItemIcon": "icon_2",
		"s_SkillName": "测试技能198"
	},
	{
		"i_Id": 170203,
		"i_SkillId": 170203,
		"i_SkillLevel": 1,
		"s_ItemIcon": "icon_3",
		"s_SkillName": "测试技能199"
	},
	{
		"i_Id": 170204,
		"i_SkillId": 170204,
		"i_SkillLevel": 1,
		"s_ItemIcon": "icon_4",
		"s_SkillName": "测试技能200"
	},
	{
		"i_Id": 170301,
		"i_SkillId": 170301,
		"i_SkillLevel": 1,
		"s_ItemIcon": "icon_1",
		"s_SkillName": "测试技能201"
	},
	{
		"i_Id": 170302,
		"i_SkillId": 170302,
		"i_SkillLevel": 1,
		"s_ItemIcon": "icon_2",
		"s_SkillName": "测试技能202"
	},
	{
		"i_Id": 170303,
		"i_SkillId": 170303,
		"i_SkillLevel": 1,
		"s_ItemIcon": "icon_3",
		"s_SkillName": "测试技能203"
	},
	{
		"i_Id": 170304,
		"i_SkillId": 170304,
		"i_SkillLevel": 1,
		"s_ItemIcon": "icon_4",
		"s_SkillName": "测试技能204"
	},
	{
		"i_Id": 170401,
		"i_SkillId": 170401,
		"i_SkillLevel": 1,
		"s_ItemIcon": "icon_1",
		"s_SkillName": "测试技能205"
	},
	{
		"i_Id": 170402,
		"i_SkillId": 170402,
		"i_SkillLevel": 1,
		"s_ItemIcon": "icon_2",
		"s_SkillName": "测试技能206"
	},
	{
		"i_Id": 170403,
		"i_SkillId": 170403,
		"i_SkillLevel": 1,
		"s_ItemIcon": "icon_3",
		"s_SkillName": "测试技能207"
	},
	{
		"i_Id": 170404,
		"i_SkillId": 170404,
		"i_SkillLevel": 1,
		"s_ItemIcon": "icon_4",
		"s_SkillName": "测试技能208"
	},
	{
		"i_Id": 170501,
		"i_SkillId": 170501,
		"i_SkillLevel": 1,
		"s_ItemIcon": "icon_1",
		"s_SkillName": "测试技能209"
	},
	{
		"i_Id": 170502,
		"i_SkillId": 170502,
		"i_SkillLevel": 1,
		"s_ItemIcon": "icon_2",
		"s_SkillName": "测试技能210"
	},
	{
		"i_Id": 170503,
		"i_SkillId": 170503,
		"i_SkillLevel": 1,
		"s_ItemIcon": "icon_3",
		"s_SkillName": "测试技能211"
	},
	{
		"i_Id": 170504,
		"i_SkillId": 170504,
		"i_SkillLevel": 1,
		"s_ItemIcon": "icon_4",
		"s_SkillName": "测试技能212"
	},
	{
		"i_Id": 170505,
		"i_SkillId": 170505,
		"i_SkillLevel": 1,
		"s_ItemIcon": "icon_5",
		"s_SkillName": "测试技能213"
	},
	{
		"i_Id": 170601,
		"i_SkillId": 170601,
		"i_SkillLevel": 1,
		"s_ItemIcon": "icon_1",
		"s_SkillName": "测试技能214"
	},
	{
		"i_Id": 170602,
		"i_SkillId": 170602,
		"i_SkillLevel": 1,
		"s_ItemIcon": "icon_2",
		"s_SkillName": "测试技能215"
	},
	{
		"i_Id": 170603,
		"i_SkillId": 170603,
		"i_SkillLevel": 1,
		"s_ItemIcon": "icon_3",
		"s_SkillName": "测试技能216"
	},
	{
		"i_Id": 170604,
		"i_SkillId": 170604,
		"i_SkillLevel": 1,
		"s_ItemIcon": "icon_4",
		"s_SkillName": "测试技能217"
	},
	{
		"i_Id": 170605,
		"i_SkillId": 170605,
		"i_SkillLevel": 1,
		"s_ItemIcon": "icon_5",
		"s_SkillName": "测试技能218"
	},
	{
		"i_Id": 170701,
		"i_SkillId": 170701,
		"i_SkillLevel": 1,
		"s_ItemIcon": "icon_1",
		"s_SkillName": "测试技能219"
	},
	{
		"i_Id": 170702,
		"i_SkillId": 170702,
		"i_SkillLevel": 1,
		"s_ItemIcon": "icon_2",
		"s_SkillName": "测试技能220"
	},
	{
		"i_Id": 170703,
		"i_SkillId": 170703,
		"i_SkillLevel": 1,
		"s_ItemIcon": "icon_3",
		"s_SkillName": "测试技能221"
	},
	{
		"i_Id": 170704,
		"i_SkillId": 170704,
		"i_SkillLevel": 1,
		"s_ItemIcon": "icon_4",
		"s_SkillName": "测试技能222"
	},
	{
		"i_Id": 170705,
		"i_SkillId": 170705,
		"i_SkillLevel": 1,
		"s_ItemIcon": "icon_5",
		"s_SkillName": "测试技能223"
	},
	{
		"i_Id": 170801,
		"i_SkillId": 170801,
		"i_SkillLevel": 1,
		"s_ItemIcon": "icon_1",
		"s_SkillName": "测试技能224"
	},
	{
		"i_Id": 170802,
		"i_SkillId": 170802,
		"i_SkillLevel": 1,
		"s_ItemIcon": "icon_2",
		"s_SkillName": "测试技能225"
	},
	{
		"i_Id": 170803,
		"i_SkillId": 170803,
		"i_SkillLevel": 1,
		"s_ItemIcon": "icon_3",
		"s_SkillName": "测试技能226"
	},
	{
		"i_Id": 170804,
		"i_SkillId": 170804,
		"i_SkillLevel": 1,
		"s_ItemIcon": "icon_4",
		"s_SkillName": "测试技能227"
	},
	{
		"i_Id": 170805,
		"i_SkillId": 170805,
		"i_SkillLevel": 1,
		"s_ItemIcon": "icon_5",
		"s_SkillName": "测试技能228"
	},
	{
		"i_Id": 170901,
		"i_SkillId": 170901,
		"i_SkillLevel": 1,
		"s_ItemIcon": "icon_1",
		"s_SkillName": "测试技能229"
	},
	{
		"i_Id": 170902,
		"i_SkillId": 170902,
		"i_SkillLevel": 1,
		"s_ItemIcon": "icon_2",
		"s_SkillName": "测试技能230"
	},
	{
		"i_Id": 170903,
		"i_SkillId": 170903,
		"i_SkillLevel": 1,
		"s_ItemIcon": "icon_3",
		"s_SkillName": "测试技能231"
	},
	{
		"i_Id": 170904,
		"i_SkillId": 170904,
		"i_SkillLevel": 1,
		"s_ItemIcon": "icon_4",
		"s_SkillName": "测试技能232"
	},
	{
		"i_Id": 170905,
		"i_SkillId": 170905,
		"i_SkillLevel": 1,
		"s_ItemIcon": "icon_5",
		"s_SkillName": "测试技能233"
	},
	{
		"i_Id": 170906,
		"i_SkillId": 170906,
		"i_SkillLevel": 1,
		"s_ItemIcon": "icon_6",
		"s_SkillName": "测试技能234"
	},
	{
		"i_Id": 171001,
		"i_SkillId": 171001,
		"i_SkillLevel": 1,
		"s_ItemIcon": "icon_1",
		"s_SkillName": "测试技能235"
	},
	{
		"i_Id": 171002,
		"i_SkillId": 171002,
		"i_SkillLevel": 1,
		"s_ItemIcon": "icon_2",
		"s_SkillName": "测试技能236"
	},
	{
		"i_Id": 171003,
		"i_SkillId": 171003,
		"i_SkillLevel": 1,
		"s_ItemIcon": "icon_3",
		"s_SkillName": "测试技能237"
	},
	{
		"i_Id": 171004,
		"i_SkillId": 171004,
		"i_SkillLevel": 1,
		"s_ItemIcon": "icon_4",
		"s_SkillName": "测试技能238"
	},
	{
		"i_Id": 171005,
		"i_SkillId": 171005,
		"i_SkillLevel": 1,
		"s_ItemIcon": "icon_5",
		"s_SkillName": "测试技能239"
	},
	{
		"i_Id": 171006,
		"i_SkillId": 171006,
		"i_SkillLevel": 1,
		"s_ItemIcon": "icon_6",
		"s_SkillName": "测试技能240"
	},
	{
		"i_Id": 171101,
		"i_SkillId": 171101,
		"i_SkillLevel": 1,
		"s_ItemIcon": "icon_1",
		"s_SkillName": "测试技能241"
	},
	{
		"i_Id": 171102,
		"i_SkillId": 171102,
		"i_SkillLevel": 1,
		"s_ItemIcon": "icon_2",
		"s_SkillName": "测试技能242"
	},
	{
		"i_Id": 171103,
		"i_SkillId": 171103,
		"i_SkillLevel": 1,
		"s_ItemIcon": "icon_3",
		"s_SkillName": "测试技能243"
	},
	{
		"i_Id": 171104,
		"i_SkillId": 171104,
		"i_SkillLevel": 1,
		"s_ItemIcon": "icon_4",
		"s_SkillName": "测试技能244"
	},
	{
		"i_Id": 171105,
		"i_SkillId": 171105,
		"i_SkillLevel": 1,
		"s_ItemIcon": "icon_5",
		"s_SkillName": "测试技能245"
	},
	{
		"i_Id": 171106,
		"i_SkillId": 171106,
		"i_SkillLevel": 1,
		"s_ItemIcon": "icon_6",
		"s_SkillName": "测试技能246"
	},
	{
		"i_Id": 171107,
		"i_SkillId": 171107,
		"i_SkillLevel": 1,
		"s_ItemIcon": "icon_7",
		"s_SkillName": "测试技能247"
	},
	{
		"i_Id": 171108,
		"i_SkillId": 171108,
		"i_SkillLevel": 1,
		"s_ItemIcon": "icon_8",
		"s_SkillName": "测试技能248"
	},
	{
		"i_Id": 171201,
		"i_SkillId": 171201,
		"i_SkillLevel": 1,
		"s_ItemIcon": "icon_1",
		"s_SkillName": "测试技能249"
	},
	{
		"i_Id": 171202,
		"i_SkillId": 171202,
		"i_SkillLevel": 1,
		"s_ItemIcon": "icon_2",
		"s_SkillName": "测试技能250"
	},
	{
		"i_Id": 171203,
		"i_SkillId": 171203,
		"i_SkillLevel": 1,
		"s_ItemIcon": "icon_3",
		"s_SkillName": "测试技能251"
	},
	{
		"i_Id": 171204,
		"i_SkillId": 171204,
		"i_SkillLevel": 1,
		"s_ItemIcon": "icon_4",
		"s_SkillName": "测试技能252"
	},
	{
		"i_Id": 171205,
		"i_SkillId": 171205,
		"i_SkillLevel": 1,
		"s_ItemIcon": "icon_5",
		"s_SkillName": "测试技能253"
	},
	{
		"i_Id": 171206,
		"i_SkillId": 171206,
		"i_SkillLevel": 1,
		"s_ItemIcon": "icon_6",
		"s_SkillName": "测试技能254"
	},
	{
		"i_Id": 171207,
		"i_SkillId": 171207,
		"i_SkillLevel": 1,
		"s_ItemIcon": "icon_7",
		"s_SkillName": "测试技能255"
	},
	{
		"i_Id": 171208,
		"i_SkillId": 171208,
		"i_SkillLevel": 1,
		"s_ItemIcon": "icon_8",
		"s_SkillName": "测试技能256"
	},
	{
		"i_Id": 180101,
		"i_SkillId": 180101,
		"i_SkillLevel": 1,
		"s_ItemIcon": "icon_1",
		"s_SkillName": "测试技能257"
	},
	{
		"i_Id": 180102,
		"i_SkillId": 180102,
		"i_SkillLevel": 1,
		"s_ItemIcon": "icon_2",
		"s_SkillName": "测试技能258"
	},
	{
		"i_Id": 180103,
		"i_SkillId": 180103,
		"i_SkillLevel": 1,
		"s_ItemIcon": "icon_3",
		"s_SkillName": "测试技能259"
	},
	{
		"i_Id": 180104,
		"i_SkillId": 180104,
		"i_SkillLevel": 1,
		"s_ItemIcon": "icon_4",
		"s_SkillName": "测试技能260"
	},
	{
		"i_Id": 180201,
		"i_SkillId": 180201,
		"i_SkillLevel": 1,
		"s_ItemIcon": "icon_1",
		"s_SkillName": "测试技能261"
	},
	{
		"i_Id": 180202,
		"i_SkillId": 180202,
		"i_SkillLevel": 1,
		"s_ItemIcon": "icon_2",
		"s_SkillName": "测试技能262"
	},
	{
		"i_Id": 180203,
		"i_SkillId": 180203,
		"i_SkillLevel": 1,
		"s_ItemIcon": "icon_3",
		"s_SkillName": "测试技能263"
	},
	{
		"i_Id": 180204,
		"i_SkillId": 180204,
		"i_SkillLevel": 1,
		"s_ItemIcon": "icon_4",
		"s_SkillName": "测试技能264"
	},
	{
		"i_Id": 180301,
		"i_SkillId": 180301,
		"i_SkillLevel": 1,
		"s_ItemIcon": "icon_1",
		"s_SkillName": "测试技能265"
	},
	{
		"i_Id": 180302,
		"i_SkillId": 180302,
		"i_SkillLevel": 1,
		"s_ItemIcon": "icon_2",
		"s_SkillName": "测试技能266"
	},
	{
		"i_Id": 180303,
		"i_SkillId": 180303,
		"i_SkillLevel": 1,
		"s_ItemIcon": "icon_3",
		"s_SkillName": "测试技能267"
	},
	{
		"i_Id": 180304,
		"i_SkillId": 180304,
		"i_SkillLevel": 1,
		"s_ItemIcon": "icon_4",
		"s_SkillName": "测试技能268"
	},
	{
		"i_Id": 180401,
		"i_SkillId": 180401,
		"i_SkillLevel": 1,
		"s_ItemIcon": "icon_1",
		"s_SkillName": "测试技能269"
	},
	{
		"i_Id": 180402,
		"i_SkillId": 180402,
		"i_SkillLevel": 1,
		"s_ItemIcon": "icon_2",
		"s_SkillName": "测试技能270"
	},
	{
		"i_Id": 180403,
		"i_SkillId": 180403,
		"i_SkillLevel": 1,
		"s_ItemIcon": "icon_3",
		"s_SkillName": "测试技能271"
	},
	{
		"i_Id": 180404,
		"i_SkillId": 180404,
		"i_SkillLevel": 1,
		"s_ItemIcon": "icon_4",
		"s_SkillName": "测试技能272"
	},
	{
		"i_Id": 180501,
		"i_SkillId": 180501,
		"i_SkillLevel": 1,
		"s_ItemIcon": "icon_1",
		"s_SkillName": "测试技能273"
	},
	{
		"i_Id": 180502,
		"i_SkillId": 180502,
		"i_SkillLevel": 1,
		"s_ItemIcon": "icon_2",
		"s_SkillName": "测试技能274"
	},
	{
		"i_Id": 180503,
		"i_SkillId": 180503,
		"i_SkillLevel": 1,
		"s_ItemIcon": "icon_3",
		"s_SkillName": "测试技能275"
	},
	{
		"i_Id": 180504,
		"i_SkillId": 180504,
		"i_SkillLevel": 1,
		"s_ItemIcon": "icon_4",
		"s_SkillName": "测试技能276"
	},
	{
		"i_Id": 180505,
		"i_SkillId": 180505,
		"i_SkillLevel": 1,
		"s_ItemIcon": "icon_5",
		"s_SkillName": "测试技能277"
	},
	{
		"i_Id": 180601,
		"i_SkillId": 180601,
		"i_SkillLevel": 1,
		"s_ItemIcon": "icon_1",
		"s_SkillName": "测试技能278"
	},
	{
		"i_Id": 180602,
		"i_SkillId": 180602,
		"i_SkillLevel": 1,
		"s_ItemIcon": "icon_2",
		"s_SkillName": "测试技能279"
	},
	{
		"i_Id": 180603,
		"i_SkillId": 180603,
		"i_SkillLevel": 1,
		"s_ItemIcon": "icon_3",
		"s_SkillName": "测试技能280"
	},
	{
		"i_Id": 180604,
		"i_SkillId": 180604,
		"i_SkillLevel": 1,
		"s_ItemIcon": "icon_4",
		"s_SkillName": "测试技能281"
	},
	{
		"i_Id": 180605,
		"i_SkillId": 180605,
		"i_SkillLevel": 1,
		"s_ItemIcon": "icon_5",
		"s_SkillName": "测试技能282"
	},
	{
		"i_Id": 180701,
		"i_SkillId": 180701,
		"i_SkillLevel": 1,
		"s_ItemIcon": "icon_1",
		"s_SkillName": "测试技能283"
	},
	{
		"i_Id": 180702,
		"i_SkillId": 180702,
		"i_SkillLevel": 1,
		"s_ItemIcon": "icon_2",
		"s_SkillName": "测试技能284"
	},
	{
		"i_Id": 180703,
		"i_SkillId": 180703,
		"i_SkillLevel": 1,
		"s_ItemIcon": "icon_3",
		"s_SkillName": "测试技能285"
	},
	{
		"i_Id": 180704,
		"i_SkillId": 180704,
		"i_SkillLevel": 1,
		"s_ItemIcon": "icon_4",
		"s_SkillName": "测试技能286"
	},
	{
		"i_Id": 180705,
		"i_SkillId": 180705,
		"i_SkillLevel": 1,
		"s_ItemIcon": "icon_5",
		"s_SkillName": "测试技能287"
	},
	{
		"i_Id": 180801,
		"i_SkillId": 180801,
		"i_SkillLevel": 1,
		"s_ItemIcon": "icon_1",
		"s_SkillName": "测试技能288"
	},
	{
		"i_Id": 180802,
		"i_SkillId": 180802,
		"i_SkillLevel": 1,
		"s_ItemIcon": "icon_2",
		"s_SkillName": "测试技能289"
	},
	{
		"i_Id": 180803,
		"i_SkillId": 180803,
		"i_SkillLevel": 1,
		"s_ItemIcon": "icon_3",
		"s_SkillName": "测试技能290"
	},
	{
		"i_Id": 180804,
		"i_SkillId": 180804,
		"i_SkillLevel": 1,
		"s_ItemIcon": "icon_4",
		"s_SkillName": "测试技能291"
	},
	{
		"i_Id": 180805,
		"i_SkillId": 180805,
		"i_SkillLevel": 1,
		"s_ItemIcon": "icon_5",
		"s_SkillName": "测试技能292"
	},
	{
		"i_Id": 180901,
		"i_SkillId": 180901,
		"i_SkillLevel": 1,
		"s_ItemIcon": "icon_1",
		"s_SkillName": "测试技能293"
	},
	{
		"i_Id": 180902,
		"i_SkillId": 180902,
		"i_SkillLevel": 1,
		"s_ItemIcon": "icon_2",
		"s_SkillName": "测试技能294"
	},
	{
		"i_Id": 180903,
		"i_SkillId": 180903,
		"i_SkillLevel": 1,
		"s_ItemIcon": "icon_3",
		"s_SkillName": "测试技能295"
	},
	{
		"i_Id": 180904,
		"i_SkillId": 180904,
		"i_SkillLevel": 1,
		"s_ItemIcon": "icon_4",
		"s_SkillName": "测试技能296"
	},
	{
		"i_Id": 180905,
		"i_SkillId": 180905,
		"i_SkillLevel": 1,
		"s_ItemIcon": "icon_5",
		"s_SkillName": "测试技能297"
	},
	{
		"i_Id": 180906,
		"i_SkillId": 180906,
		"i_SkillLevel": 1,
		"s_ItemIcon": "icon_6",
		"s_SkillName": "测试技能298"
	},
	{
		"i_Id": 181001,
		"i_SkillId": 181001,
		"i_SkillLevel": 1,
		"s_ItemIcon": "icon_1",
		"s_SkillName": "测试技能299"
	},
	{
		"i_Id": 181002,
		"i_SkillId": 181002,
		"i_SkillLevel": 1,
		"s_ItemIcon": "icon_2",
		"s_SkillName": "测试技能300"
	},
	{
		"i_Id": 181003,
		"i_SkillId": 181003,
		"i_SkillLevel": 1,
		"s_ItemIcon": "icon_3",
		"s_SkillName": "测试技能301"
	},
	{
		"i_Id": 181004,
		"i_SkillId": 181004,
		"i_SkillLevel": 1,
		"s_ItemIcon": "icon_4",
		"s_SkillName": "测试技能302"
	},
	{
		"i_Id": 181005,
		"i_SkillId": 181005,
		"i_SkillLevel": 1,
		"s_ItemIcon": "icon_5",
		"s_SkillName": "测试技能303"
	},
	{
		"i_Id": 181006,
		"i_SkillId": 181006,
		"i_SkillLevel": 1,
		"s_ItemIcon": "icon_6",
		"s_SkillName": "测试技能304"
	},
	{
		"i_Id": 181101,
		"i_SkillId": 181101,
		"i_SkillLevel": 1,
		"s_ItemIcon": "icon_1",
		"s_SkillName": "测试技能305"
	},
	{
		"i_Id": 181102,
		"i_SkillId": 181102,
		"i_SkillLevel": 1,
		"s_ItemIcon": "icon_2",
		"s_SkillName": "测试技能306"
	},
	{
		"i_Id": 181103,
		"i_SkillId": 181103,
		"i_SkillLevel": 1,
		"s_ItemIcon": "icon_3",
		"s_SkillName": "测试技能307"
	},
	{
		"i_Id": 181104,
		"i_SkillId": 181104,
		"i_SkillLevel": 1,
		"s_ItemIcon": "icon_4",
		"s_SkillName": "测试技能308"
	},
	{
		"i_Id": 181105,
		"i_SkillId": 181105,
		"i_SkillLevel": 1,
		"s_ItemIcon": "icon_5",
		"s_SkillName": "测试技能309"
	},
	{
		"i_Id": 181106,
		"i_SkillId": 181106,
		"i_SkillLevel": 1,
		"s_ItemIcon": "icon_6",
		"s_SkillName": "测试技能310"
	},
	{
		"i_Id": 181107,
		"i_SkillId": 181107,
		"i_SkillLevel": 1,
		"s_ItemIcon": "icon_7",
		"s_SkillName": "测试技能311"
	},
	{
		"i_Id": 181108,
		"i_SkillId": 181108,
		"i_SkillLevel": 1,
		"s_ItemIcon": "icon_8",
		"s_SkillName": "测试技能312"
	},
	{
		"i_Id": 181201,
		"i_SkillId": 181201,
		"i_SkillLevel": 1,
		"s_ItemIcon": "icon_1",
		"s_SkillName": "测试技能313"
	},
	{
		"i_Id": 181202,
		"i_SkillId": 181202,
		"i_SkillLevel": 1,
		"s_ItemIcon": "icon_2",
		"s_SkillName": "测试技能314"
	},
	{
		"i_Id": 181203,
		"i_SkillId": 181203,
		"i_SkillLevel": 1,
		"s_ItemIcon": "icon_3",
		"s_SkillName": "测试技能315"
	},
	{
		"i_Id": 181204,
		"i_SkillId": 181204,
		"i_SkillLevel": 1,
		"s_ItemIcon": "icon_4",
		"s_SkillName": "测试技能316"
	},
	{
		"i_Id": 181205,
		"i_SkillId": 181205,
		"i_SkillLevel": 1,
		"s_ItemIcon": "icon_5",
		"s_SkillName": "测试技能317"
	},
	{
		"i_Id": 181206,
		"i_SkillId": 181206,
		"i_SkillLevel": 1,
		"s_ItemIcon": "icon_6",
		"s_SkillName": "测试技能318"
	},
	{
		"i_Id": 181207,
		"i_SkillId": 181207,
		"i_SkillLevel": 1,
		"s_ItemIcon": "icon_7",
		"s_SkillName": "测试技能319"
	},
	{
		"i_Id": 181208,
		"i_SkillId": 181208,
		"i_SkillLevel": 1,
		"s_ItemIcon": "icon_8",
		"s_SkillName": "测试技能320"
	}
]